<?xml version="1.0" encoding="utf-8"?>
<Libraries>
  <Library>
    <systemid>Kyoto_Ayabe</systemid>
    <systemname>京都府綾部市</systemname>
    <libkey>綾部図書館</libkey>
    <libid>102199</libid>
    <short>綾部市図書館</short>
    <formal>綾部市図書館</formal>
    <url_pc>https://ayabe-library.com/</url_pc>
    <address>京都府綾部市新町91</address>
    <pref>京都府</pref>
    <city>綾部市</city>
    <post>623-0022</post>
    <tel>0773-42-6980</tel>
    <geocode>135.257753,35.296964</geocode>
    <category>MEDIUM</category>
    <image/>
  </Library>
  <Library>
    <systemid>Kyoto_Fukuchiyama</systemid>
    <systemname>京都府福知山市</systemname>
    <libkey>三和分館</libkey>
    <libid>102196</libid>
    <short>三和分館</short>
    <formal>福知山市立図書館三和分館</formal>
    <url_pc>https://www.lics-saas.nexs-service.jp/city-fukuchiyama/</url_pc>
    <address>京都府福知山市三和町千束383 三和会館1F</address>
    <pref>京都府</pref>
    <city>福知山市</city>
    <post>620-1442</post>
    <tel>0773-58-4715</tel>
    <geocode>135.2355718,35.2162595</geocode>
    <category>MEDIUM</category>
    <image/>
  </Library>
  <Library>
    <systemid>Kyoto_Fukuchiyama</systemid>
    <systemname>京都府福知山市</systemname>
    <libkey>中央館</libkey>
    <libid>102198</libid>
    <short>中央館</short>
    <formal>福知山市立図書館中央館</formal>
    <url_pc>https://www.lics-saas.nexs-service.jp/city-fukuchiyama/</url_pc>
    <address>京都府福知山市駅前町400番地 市民交流プラザふくちやま「ききょう」内</address>
    <pref>京都府</pref>
    <city>福知山市</city>
    <post>620-0045</post>
    <tel>0773-22-3225</tel>
    <geocode>135.119411,35.296401</geocode>
    <category>MEDIUM</category>
    <image/>
  </Library>
  <Library>
    <systemid>Kyoto_Fukuchiyama</systemid>
    <systemname>京都府福知山市</systemname>
    <libkey>夜久野分館</libkey>
    <libid>102197</libid>
    <short>夜久野分館</short>
    <formal>福知山市立図書館夜久野分館</formal>
    <url_pc>https://www.lics-saas.nexs-service.jp/city-fukuchiyama/</url_pc>
    <address>京都府福知山市夜久野町額田19-2 夜久野ふれあいプラザ内</address>
    <pref>京都府</pref>
    <city>福知山市</city>
    <post>629-1304</post>
    <tel>0773-37-1066</tel>
    <geocode>135.002339,35.318494</geocode>
    <category>MEDIUM</category>
    <image/>
  </Library>
  <Library>
    <systemid>Kyoto_Fukuchiyama</systemid>
    <systemname>京都府福知山市</systemname>
    <libkey>大江分館</libkey>
    <libid>110834</libid>
    <short>大江分館</short>
    <formal>福知山市立図書館大江分館</formal>
    <url_pc>https://www.lics-saas.nexs-service.jp/city-fukuchiyama/</url_pc>
    <address>京都府福知山市大江町河守285 大江町総合会館内</address>
    <pref>京都府</pref>
    <city>福知山市</city>
    <post>620-0301</post>
    <tel>0773-56-1017</tel>
    <geocode>135.147733,35.389450</geocode>
    <category>MEDIUM</category>
    <image/>
  </Library>
  <Library>
    <systemid>Kyoto_Ide</systemid>
    <systemname>京都府井手町</systemname>
    <libkey>井手町図書館</libkey>
    <libid>102111</libid>
    <short>井手町図書館</short>
    <formal>井手町図書館</formal>
    <url_pc>http://www.town.ide.kyoto.jp/soshiki/kyouikuiinkai/syakaikyouiku/shisetsu/1394790426601.html</url_pc>
    <address>京都府綴喜郡井手町井手二本松3-1 山吹ふれあいセンター内</address>
    <pref>京都府</pref>
    <city>綴喜郡井手町</city>
    <post>610-0302</post>
    <tel>0774-82-5700</tel>
    <geocode>135.814396,34.8055271</geocode>
    <category>MEDIUM</category>
    <image/>
  </Library>
  <Library>
    <systemid>Kyoto_Joyo</systemid>
    <systemname>京都府城陽市</systemname>
    <libkey>今池</libkey>
    <libid>102112</libid>
    <short>今池コミュニティセンター</short>
    <formal>城陽市立今池コミュニティセンター図書室</formal>
    <url_pc>https://library.city.joyo.kyoto.jp/</url_pc>
    <address>京都府城陽市枇杷庄知原15-1</address>
    <pref>京都府</pref>
    <city>城陽市</city>
    <post>610-0117</post>
    <tel>0774-56-0525</tel>
    <geocode>135.7692138,34.8391178</geocode>
    <category>SMALL</category>
    <image/>
  </Library>
  <Library>
    <systemid>Kyoto_Joyo</systemid>
    <systemname>京都府城陽市</systemname>
    <libkey>北部</libkey>
    <libid>102113</libid>
    <short>北部コミュニティセンター</short>
    <formal>城陽市立北部コミュニティセンター図書室</formal>
    <url_pc>https://library.city.joyo.kyoto.jp/</url_pc>
    <address>京都府城陽市平川広田67</address>
    <pref>京都府</pref>
    <city>城陽市</city>
    <post>610-0101</post>
    <tel>0774-55-1001</tel>
    <geocode>135.7630032,34.8629351</geocode>
    <category>SMALL</category>
    <image/>
  </Library>
  <Library>
    <systemid>Kyoto_Joyo</systemid>
    <systemname>京都府城陽市</systemname>
    <libkey>南部</libkey>
    <libid>102114</libid>
    <short>南部コミュニティセンター</short>
    <formal>城陽市立南部コミュニティセンター図書室</formal>
    <url_pc>https://library.city.joyo.kyoto.jp/</url_pc>
    <address>京都府城陽市富野東田部70-1</address>
    <pref>京都府</pref>
    <city>城陽市</city>
    <post>610-0111</post>
    <tel>0774-55-1002</tel>
    <geocode>135.781272,34.841610</geocode>
    <category>SMALL</category>
    <image/>
  </Library>
  <Library>
    <systemid>Kyoto_Joyo</systemid>
    <systemname>京都府城陽市</systemname>
    <libkey>図書館</libkey>
    <libid>102115</libid>
    <short>城陽市立図書館</short>
    <formal>城陽市立図書館</formal>
    <url_pc>https://library.city.joyo.kyoto.jp/</url_pc>
    <address>京都府城陽市寺田今堀1</address>
    <pref>京都府</pref>
    <city>城陽市</city>
    <post>610-0121</post>
    <tel>0774-53-4000</tel>
    <geocode>135.773525,34.849105</geocode>
    <category>MEDIUM</category>
    <image/>
  </Library>
  <Library>
    <systemid>Kyoto_Joyo</systemid>
    <systemname>京都府城陽市</systemname>
    <libkey>東部</libkey>
    <libid>102116</libid>
    <short>東部コミュニティセンター</short>
    <formal>城陽市立東部コミュニティセンター図書室</formal>
    <url_pc>https://library.city.joyo.kyoto.jp/</url_pc>
    <address>京都府城陽市寺田正道152</address>
    <pref>京都府</pref>
    <city>城陽市</city>
    <post>610-0121</post>
    <tel>0774-55-7858</tel>
    <geocode>135.7804739,34.8584132</geocode>
    <category>SMALL</category>
    <image/>
  </Library>
  <Library>
    <systemid>Kyoto_Joyo</systemid>
    <systemname>京都府城陽市</systemname>
    <libkey>青谷</libkey>
    <libid>102117</libid>
    <short>青谷コミュニティセンター</short>
    <formal>城陽市立青谷コミュニティセンター図書室</formal>
    <url_pc>https://library.city.joyo.kyoto.jp/</url_pc>
    <address>京都府城陽市市辺五島7-1</address>
    <pref>京都府</pref>
    <city>城陽市</city>
    <post>610-0114</post>
    <tel>0774-53-8273</tel>
    <geocode>135.8000722,34.8283246</geocode>
    <category>SMALL</category>
    <image/>
  </Library>
  <Library>
    <systemid>Kyoto_Kameoka</systemid>
    <systemname>京都府亀岡市</systemname>
    <libkey>ガレリア分館</libkey>
    <libid>102123</libid>
    <short>ガレリア分館</short>
    <formal>亀岡市立図書館ガレリア分館</formal>
    <url_pc>https://www.library.city.kameoka.kyoto.jp/</url_pc>
    <address>京都府亀岡市余部町宝久保1番地の1 ガレリアかめおか内</address>
    <pref>京都府</pref>
    <city>亀岡市</city>
    <post>621-0806</post>
    <tel>0771-29-2702</tel>
    <geocode>135.5667514,35.0144359</geocode>
    <category>MEDIUM</category>
    <image/>
  </Library>
  <Library>
    <systemid>Kyoto_Kameoka</systemid>
    <systemname>京都府亀岡市</systemname>
    <libkey>中央館</libkey>
    <libid>102118</libid>
    <short>中央館</short>
    <formal>亀岡市立図書館中央館</formal>
    <url_pc>https://www.library.city.kameoka.kyoto.jp/</url_pc>
    <address>京都府亀岡市内丸町26</address>
    <pref>京都府</pref>
    <city>亀岡市</city>
    <post>621-0864</post>
    <tel>0771-24-4710</tel>
    <geocode>135.578371,35.013760</geocode>
    <category>MEDIUM</category>
    <image/>
  </Library>
  <Library>
    <systemid>Kyoto_Kameoka</systemid>
    <systemname>京都府亀岡市</systemname>
    <libkey>大井分館</libkey>
    <libid>102119</libid>
    <short>大井分館</short>
    <formal>亀岡市立図書館大井分館</formal>
    <url_pc>https://www.library.city.kameoka.kyoto.jp/</url_pc>
    <address>京都府亀岡市大井町土田2丁目11番20-206号</address>
    <pref>京都府</pref>
    <city>亀岡市</city>
    <post>621-0011</post>
    <tel>0771-25-8572</tel>
    <geocode>135.554110,35.032608</geocode>
    <category>MEDIUM</category>
    <image/>
  </Library>
  <Library>
    <systemid>Kyoto_Kameoka</systemid>
    <systemname>京都府亀岡市</systemname>
    <libkey>川東図書館</libkey>
    <libid>119145</libid>
    <short>川東地域図書館</short>
    <formal>亀岡市立川東地域図書館</formal>
    <url_pc>https://www.library.city.kameoka.kyoto.jp/WebOpac/webopac/infodetail.do</url_pc>
    <address>京都府亀岡市馬路町野堀1-7</address>
    <pref>京都府</pref>
    <city>亀岡市</city>
    <post>621-0008</post>
    <tel>0771-22-4389</tel>
    <geocode>135.5648799,35.0596381</geocode>
    <category>SMALL</category>
    <image/>
  </Library>
  <Library>
    <systemid>Kyoto_Kameoka</systemid>
    <systemname>京都府亀岡市</systemname>
    <libkey>西部分室</libkey>
    <libid>102120</libid>
    <short>西部分室</short>
    <formal>亀岡市立図書館西部分室</formal>
    <url_pc>https://www.library.city.kameoka.kyoto.jp/</url_pc>
    <address>京都府亀岡市本梅町井手下早田8-10 本梅生涯学習センター</address>
    <pref>京都府</pref>
    <city>亀岡市</city>
    <post>621-0253</post>
    <tel>0771-26-2332</tel>
    <geocode>135.486765,35.015318</geocode>
    <category>SMALL</category>
    <image/>
  </Library>
  <Library>
    <systemid>Kyoto_Kameoka</systemid>
    <systemname>京都府亀岡市</systemname>
    <libkey>馬堀分館</libkey>
    <libid>102121</libid>
    <short>馬堀分館</short>
    <formal>亀岡市立図書館馬堀分館</formal>
    <url_pc>https://www.library.city.kameoka.kyoto.jp/</url_pc>
    <address>京都府亀岡市篠町馬堀駅前2丁目3番1</address>
    <pref>京都府</pref>
    <city>亀岡市</city>
    <post>621-0828</post>
    <tel>0771-21-2211</tel>
    <geocode>135.603744,35.009952</geocode>
    <category>MEDIUM</category>
    <image/>
  </Library>
  <Library>
    <systemid>Kyoto_Kizugawa</systemid>
    <systemname>京都府木津川市</systemname>
    <libkey>中央図書館</libkey>
    <libid>102127</libid>
    <short>中央図書館</short>
    <formal>木津川市立中央図書館</formal>
    <url_pc>https://library.city.kizugawa.lg.jp/</url_pc>
    <address>京都府木津川市木津町内垣外36</address>
    <pref>京都府</pref>
    <city>木津川市</city>
    <post>619-0217</post>
    <tel>0774-72-2980</tel>
    <geocode>135.8150005,34.7363344</geocode>
    <category>MEDIUM</category>
    <image/>
  </Library>
  <Library>
    <systemid>Kyoto_Kizugawa</systemid>
    <systemname>京都府木津川市</systemname>
    <libkey>加茂図書館</libkey>
    <libid>102124</libid>
    <short>加茂図書館</short>
    <formal>木津川市立加茂図書館</formal>
    <url_pc>https://library.city.kizugawa.lg.jp/</url_pc>
    <address>京都府木津川市加茂町里東上田1</address>
    <pref>京都府</pref>
    <city>木津川市</city>
    <post>619-1152</post>
    <tel>0774-76-6466</tel>
    <geocode>135.866293,34.752009</geocode>
    <category>MEDIUM</category>
    <image/>
  </Library>
  <Library>
    <systemid>Kyoto_Kizugawa</systemid>
    <systemname>京都府木津川市</systemname>
    <libkey>山城図書館</libkey>
    <libid>102125</libid>
    <short>山城図書館</short>
    <formal>木津川市立山城図書館</formal>
    <url_pc>https://library.city.kizugawa.lg.jp/</url_pc>
    <address>京都府木津川市山城町平尾前田24</address>
    <pref>京都府</pref>
    <city>木津川市</city>
    <post>619-0202</post>
    <tel>0774-86-5001</tel>
    <geocode>135.8121913,34.7758492</geocode>
    <category>MEDIUM</category>
    <image/>
  </Library>
  <Library>
    <systemid>Kyoto_Kumiyama</systemid>
    <systemname>京都府久御山町</systemname>
    <libkey>久御山町立図書館</libkey>
    <libid>102185</libid>
    <short>久御山町立図書館</short>
    <formal>久御山町立図書館</formal>
    <url_pc>https://library.town.kumiyama.lg.jp/toshow/index.asp</url_pc>
    <address>京都府久世郡久御山町佐古小字外屋敷235-1</address>
    <pref>京都府</pref>
    <city>久世郡久御山町</city>
    <post>613-0031</post>
    <tel>0774-45-0003</tel>
    <geocode>135.753145,34.8813108</geocode>
    <category>MEDIUM</category>
    <image/>
  </Library>
  <Library>
    <systemid>Kyoto_Kyotamba</systemid>
    <systemname>京都府京丹波町</systemname>
    <libkey>丹波丹波</libkey>
    <libid>102184</libid>
    <short>京丹波町立中央公民館</short>
    <formal>京丹波町立中央公民館図書室</formal>
    <url_pc>http://www.town.kyotamba.kyoto.jp/</url_pc>
    <address>京都府船井郡京丹波町蒲生野口38</address>
    <pref>京都府</pref>
    <city>船井郡京丹波町</city>
    <post>622-0214</post>
    <tel>0771-82-0988</tel>
    <geocode>135.422864,35.163533</geocode>
    <category>SMALL</category>
    <image/>
  </Library>
  <Library>
    <systemid>Kyoto_Kyotanabe</systemid>
    <systemname>京都府京田辺市</systemname>
    <libkey>中央図書館</libkey>
    <libid>102135</libid>
    <short>中央図書館</short>
    <formal>京田辺市立中央図書館</formal>
    <url_pc>http://www.kyotanabe.ed.jp/nc3/c-lib/</url_pc>
    <address>京都府京田辺市田辺辻40番地</address>
    <pref>京都府</pref>
    <city>京田辺市</city>
    <post>610-0331</post>
    <tel>0774-65-2500</tel>
    <geocode>135.767487,34.820841</geocode>
    <category>MEDIUM</category>
    <image/>
  </Library>
  <Library>
    <systemid>Kyoto_Kyotanabe</systemid>
    <systemname>京都府京田辺市</systemname>
    <libkey>中部分室</libkey>
    <libid>102136</libid>
    <short>中部分室</short>
    <formal>京田辺市立中央図書館中部分室</formal>
    <url_pc>http://www.kyotanabe.ed.jp/nc3/c-lib/</url_pc>
    <address>京都府京田辺市草内美泥22番地の2 中部住民センター内</address>
    <pref>京都府</pref>
    <city>京田辺市</city>
    <post>610-0311</post>
    <tel>0774-64-8833</tel>
    <geocode>135.7877543,34.8189529</geocode>
    <category>SMALL</category>
    <image/>
  </Library>
  <Library>
    <systemid>Kyoto_Kyotanabe</systemid>
    <systemname>京都府京田辺市</systemname>
    <libkey>北部分室</libkey>
    <libid>102137</libid>
    <short>北部分室</short>
    <formal>京田辺市立中央図書館北部分室</formal>
    <url_pc>http://www.kyotanabe.ed.jp/nc3/c-lib/</url_pc>
    <address>京都府京田辺市大住内山1番地の1 北部住民センター内</address>
    <pref>京都府</pref>
    <city>京田辺市</city>
    <post>610-0343</post>
    <tel>0774-63-0499</tel>
    <geocode>135.741691,34.835609</geocode>
    <category>SMALL</category>
    <image/>
  </Library>
  <Library>
    <systemid>Kyoto_Kyotanabe</systemid>
    <systemname>京都府京田辺市</systemname>
    <libkey>移動図書館</libkey>
    <libid>102138</libid>
    <short>京田辺市移動図書館</short>
    <formal>京田辺市移動図書館</formal>
    <url_pc>http://www.kyotanabe.ed.jp/nc3/c-lib/</url_pc>
    <address>京都府京田辺市田辺辻40番地</address>
    <pref>京都府</pref>
    <city>京田辺市</city>
    <post>610-0331</post>
    <tel>0774-65-2500</tel>
    <geocode>135.7673585,34.8208583</geocode>
    <category>BM</category>
    <image/>
  </Library>
  <Library>
    <systemid>Kyoto_Kyotango</systemid>
    <systemname>京都府京丹後市</systemname>
    <libkey>あみの図書</libkey>
    <libid>102144</libid>
    <short>あみの図書館</short>
    <formal>京丹後市立あみの図書館</formal>
    <url_pc>https://www.city.kyotango.lg.jp/library/index.html</url_pc>
    <address>京都府京丹後市網野町網野385番地の1 ら・ぽーと内</address>
    <pref>京都府</pref>
    <city>京丹後市</city>
    <post>629-3101</post>
    <tel>0772-72-4946</tel>
    <geocode>135.025650,35.682208</geocode>
    <category>MEDIUM</category>
    <image/>
  </Library>
  <Library>
    <systemid>Kyoto_Kyotango</systemid>
    <systemname>京都府京丹後市</systemname>
    <libkey>たちばな</libkey>
    <libid>102145</libid>
    <short>たちばな会館</short>
    <formal>京丹後市たちばな会館図書室</formal>
    <url_pc>https://www.city.kyotango.lg.jp/library/index.html</url_pc>
    <address>京都府京丹後市網野町木津827番地</address>
    <pref>京都府</pref>
    <city>京丹後市</city>
    <post>629-3241</post>
    <tel>0772-74-0047</tel>
    <geocode>134.978260,35.652515</geocode>
    <category>SMALL</category>
    <image/>
  </Library>
  <Library>
    <systemid>Kyoto_Kyotango</systemid>
    <systemname>京都府京丹後市</systemname>
    <libkey>丹後図書室</libkey>
    <libid>102139</libid>
    <short>丹後図書室</short>
    <formal>京丹後市立丹後図書室</formal>
    <url_pc>https://www.city.kyotango.lg.jp/library/index.html</url_pc>
    <address>京都府京丹後市丹後町間人2624番地 丹後地域公民館1階</address>
    <pref>京都府</pref>
    <city>京丹後市</city>
    <post>627-0201</post>
    <tel>0772-69-0664</tel>
    <geocode>135.0905485,35.7382258</geocode>
    <category>SMALL</category>
    <image/>
  </Library>
  <Library>
    <systemid>Kyoto_Kyotango</systemid>
    <systemname>京都府京丹後市</systemname>
    <libkey>久美浜図書</libkey>
    <libid>102140</libid>
    <short>久美浜図書室</short>
    <formal>京丹後市立久美浜図書室</formal>
    <url_pc>https://www.city.kyotango.lg.jp/library/index.html</url_pc>
    <address>京都府京丹後市久美浜町852番地の1 久美浜地域公民館1階</address>
    <pref>京都府</pref>
    <city>京丹後市</city>
    <post>629-3410</post>
    <tel>0772-82-1771</tel>
    <geocode>134.896291,35.605255</geocode>
    <category>SMALL</category>
    <image/>
  </Library>
  <Library>
    <systemid>Kyoto_Kyotango</systemid>
    <systemname>京都府京丹後市</systemname>
    <libkey>大宮図書室</libkey>
    <libid>102141</libid>
    <short>大宮図書室</short>
    <formal>京丹後市大宮図書室</formal>
    <url_pc>https://www.city.kyotango.lg.jp/library/index.html</url_pc>
    <address>京都府京丹後市大宮町口大野228番地の1 アグリセンター大宮1階</address>
    <pref>京都府</pref>
    <city>京丹後市</city>
    <post>629-2501</post>
    <tel>0772-69-0672</tel>
    <geocode>135.096120,35.583907</geocode>
    <category>SMALL</category>
    <image/>
  </Library>
  <Library>
    <systemid>Kyoto_Kyotango</systemid>
    <systemname>京都府京丹後市</systemname>
    <libkey>峰山図書館</libkey>
    <libid>102142</libid>
    <short>峰山図書館</short>
    <formal>京丹後市立峰山図書館</formal>
    <url_pc>https://www.city.kyotango.lg.jp/library/index.html</url_pc>
    <address>京都府京丹後市峰山町杉谷1030番地 峰山地域公民館3階</address>
    <pref>京都府</pref>
    <city>京丹後市</city>
    <post>627-0012</post>
    <tel>0772-62-5101</tel>
    <geocode>135.070727,35.624601</geocode>
    <category>MEDIUM</category>
    <image/>
  </Library>
  <Library>
    <systemid>Kyoto_Kyotango</systemid>
    <systemname>京都府京丹後市</systemname>
    <libkey>弥栄図書室</libkey>
    <libid>102143</libid>
    <short>弥栄図書室</short>
    <formal>京丹後市弥栄図書室</formal>
    <url_pc>https://www.city.kyotango.lg.jp/library/index.html</url_pc>
    <address>京都府京丹後市弥栄町溝谷3443番地の2 弥栄地域公民館1階</address>
    <pref>京都府</pref>
    <city>京丹後市</city>
    <post>627-0111</post>
    <tel>0772-65-2101</tel>
    <geocode>135.092141,35.658599</geocode>
    <category>SMALL</category>
    <image/>
  </Library>
  <Library>
    <systemid>Kyoto_Kyoto</systemid>
    <systemname>京都府京都市</systemname>
    <libkey>みらい館</libkey>
    <libid>102146</libid>
    <short>こどもみらい館子育て図書館</short>
    <formal>京都市こどもみらい館子育て図書館</formal>
    <url_pc>https://www2.kyotocitylib.jp/</url_pc>
    <address>京都府京都市中京区間之町通竹屋町下る楠町601-1</address>
    <pref>京都府</pref>
    <city>京都市</city>
    <post>604-0883</post>
    <tel>075-254-8181</tel>
    <geocode>135.761189,35.015541</geocode>
    <category>MEDIUM</category>
    <image/>
  </Library>
  <Library>
    <systemid>Kyoto_Kyoto</systemid>
    <systemname>京都府京都市</systemname>
    <libkey>下京</libkey>
    <libid>102147</libid>
    <short>下京図書館</short>
    <formal>京都市下京図書館</formal>
    <url_pc>https://www2.kyotocitylib.jp/</url_pc>
    <address>京都府京都市下京区新町通松原下る富永町110-1 下京修徳ふれあい福祉会館4階</address>
    <pref>京都府</pref>
    <city>京都市</city>
    <post>600-8449</post>
    <tel>075-351-8196</tel>
    <geocode>135.756942,34.997995</geocode>
    <category>MEDIUM</category>
    <image/>
  </Library>
  <Library>
    <systemid>Kyoto_Kyoto</systemid>
    <systemname>京都府京都市</systemname>
    <libkey>中央</libkey>
    <libid>102148</libid>
    <short>中央図書館</short>
    <formal>京都市中央図書館</formal>
    <url_pc>https://www2.kyotocitylib.jp/</url_pc>
    <address>京都府京都市中京区聚楽廻松下町9-2</address>
    <pref>京都府</pref>
    <city>京都市</city>
    <post>604-8401</post>
    <tel>075-802-3133</tel>
    <geocode>135.738442,35.019038</geocode>
    <category>MEDIUM</category>
    <image/>
  </Library>
  <Library>
    <systemid>Kyoto_Kyoto</systemid>
    <systemname>京都府京都市</systemname>
    <libkey>久世</libkey>
    <libid>102149</libid>
    <short>久世ふれあいセンター図書館</short>
    <formal>京都市久世ふれあいセンター図書館</formal>
    <url_pc>https://www2.kyotocitylib.jp/</url_pc>
    <address>京都府京都市南区久世築山町328 久世ふれあいセンター1階</address>
    <pref>京都府</pref>
    <city>京都市</city>
    <post>601-8203</post>
    <tel>075-931-0035</tel>
    <geocode>135.724406,34.958234</geocode>
    <category>MEDIUM</category>
    <image/>
  </Library>
  <Library>
    <systemid>Kyoto_Kyoto</systemid>
    <systemname>京都府京都市</systemname>
    <libkey>久我</libkey>
    <libid>102150</libid>
    <short>久我のもり図書館</short>
    <formal>京都市久我のもり図書館</formal>
    <url_pc>https://www2.kyotocitylib.jp/</url_pc>
    <address>京都府京都市伏見区久我東町216 久我の杜生涯学習プラザ1階</address>
    <pref>京都府</pref>
    <city>京都市</city>
    <post>612-8494</post>
    <tel>075-934-2306</tel>
    <geocode>135.728682,34.9352516</geocode>
    <category>MEDIUM</category>
    <image/>
  </Library>
  <Library>
    <systemid>Kyoto_Kyoto</systemid>
    <systemname>京都府京都市</systemname>
    <libkey>伏中</libkey>
    <libid>102151</libid>
    <short>伏見中央図書館</short>
    <formal>京都市伏見中央図書館</formal>
    <url_pc>https://www2.kyotocitylib.jp/</url_pc>
    <address>京都府京都市伏見区今町659-1</address>
    <pref>京都府</pref>
    <city>京都市</city>
    <post>612-8051</post>
    <tel>075-622-6700</tel>
    <geocode>135.761848,34.935489</geocode>
    <category>MEDIUM</category>
    <image/>
  </Library>
  <Library>
    <systemid>Kyoto_Kyoto</systemid>
    <systemname>京都府京都市</systemname>
    <libkey>北</libkey>
    <libid>102152</libid>
    <short>北図書館</short>
    <formal>京都市北図書館</formal>
    <url_pc>https://www2.kyotocitylib.jp/</url_pc>
    <address>京都府京都市北区紫野雲林院町44-1 北区合同福祉センター2階</address>
    <pref>京都府</pref>
    <city>京都市</city>
    <post>603-8214</post>
    <tel>075-492-8810</tel>
    <geocode>135.749664,35.040931</geocode>
    <category>MEDIUM</category>
    <image/>
  </Library>
  <Library>
    <systemid>Kyoto_Kyoto</systemid>
    <systemname>京都府京都市</systemname>
    <libkey>南</libkey>
    <libid>102153</libid>
    <short>南図書館</short>
    <formal>京都市南図書館</formal>
    <url_pc>https://www2.kyotocitylib.jp/</url_pc>
    <address>京都府京都市南区東九条南山王町5-5</address>
    <pref>京都府</pref>
    <city>京都市</city>
    <post>601-8011</post>
    <tel>075-691-6888</tel>
    <geocode>135.7614301,34.9811753</geocode>
    <category>MEDIUM</category>
    <image/>
  </Library>
  <Library>
    <systemid>Kyoto_Kyoto</systemid>
    <systemname>京都府京都市</systemname>
    <libkey>右中</libkey>
    <libid>102154</libid>
    <short>右京中央図書館</short>
    <formal>京都市右京中央図書館</formal>
    <url_pc>https://www2.kyotocitylib.jp/</url_pc>
    <address>京都府京都市右京区太秦下刑部12番地 サンサ右京3階</address>
    <pref>京都府</pref>
    <city>京都市</city>
    <post>616-8104</post>
    <tel>075-871-5336</tel>
    <geocode>135.7160558,35.0101139</geocode>
    <category>MEDIUM</category>
    <image/>
  </Library>
  <Library>
    <systemid>Kyoto_Kyoto</systemid>
    <systemname>京都府京都市</systemname>
    <libkey>吉祥院</libkey>
    <libid>102155</libid>
    <short>吉祥院図書館</short>
    <formal>京都市吉祥院図書館</formal>
    <url_pc>https://www2.kyotocitylib.jp/</url_pc>
    <address>京都府京都市南区吉祥院池田町1 塔南高校東館1階</address>
    <pref>京都府</pref>
    <city>京都市</city>
    <post>601-8349</post>
    <tel>075-681-1281</tel>
    <geocode>135.734415,34.968052</geocode>
    <category>MEDIUM</category>
    <image/>
  </Library>
  <Library>
    <systemid>Kyoto_Kyoto</systemid>
    <systemname>京都府京都市</systemname>
    <libkey>向島</libkey>
    <libid>102156</libid>
    <short>向島図書館</short>
    <formal>京都市向島図書館</formal>
    <url_pc>https://www2.kyotocitylib.jp/</url_pc>
    <address>京都府京都市伏見区向島二ノ丸町151-35</address>
    <pref>京都府</pref>
    <city>京都市</city>
    <post>612-8141</post>
    <tel>075-622-7001</tel>
    <geocode>135.7730392,34.9172929</geocode>
    <category>MEDIUM</category>
    <image/>
  </Library>
  <Library>
    <systemid>Kyoto_Kyoto</systemid>
    <systemname>京都府京都市</systemname>
    <libkey>山科</libkey>
    <libid>102157</libid>
    <short>山科図書館</short>
    <formal>京都市山科図書館</formal>
    <url_pc>https://www2.kyotocitylib.jp/</url_pc>
    <address>京都府京都市山科区竹鼻四丁野町34-1 山科合同福祉センター4階</address>
    <pref>京都府</pref>
    <city>京都市</city>
    <post>607-8086</post>
    <tel>075-581-0503</tel>
    <geocode>135.816275,34.986531</geocode>
    <category>MEDIUM</category>
    <image/>
  </Library>
  <Library>
    <systemid>Kyoto_Kyoto</systemid>
    <systemname>京都府京都市</systemname>
    <libkey>岩倉</libkey>
    <libid>102158</libid>
    <short>岩倉図書館</short>
    <formal>京都市岩倉図書館</formal>
    <url_pc>https://www2.kyotocitylib.jp/</url_pc>
    <address>京都府京都市左京区岩倉下在地町16</address>
    <pref>京都府</pref>
    <city>京都市</city>
    <post>606-0013</post>
    <tel>075-702-8510</tel>
    <geocode>135.7858575,35.0745462</geocode>
    <category>MEDIUM</category>
    <image/>
  </Library>
  <Library>
    <systemid>Kyoto_Kyoto</systemid>
    <systemname>京都府京都市</systemname>
    <libkey>左京</libkey>
    <libid>102159</libid>
    <short>左京図書館</short>
    <formal>京都市左京図書館</formal>
    <url_pc>https://www2.kyotocitylib.jp/</url_pc>
    <address>京都府京都市左京区高野西開町5 左京合同福祉センター2階</address>
    <pref>京都府</pref>
    <city>京都市</city>
    <post>606-8103</post>
    <tel>075-722-4032</tel>
    <geocode>135.778067,35.038098</geocode>
    <category>MEDIUM</category>
    <image/>
  </Library>
  <Library>
    <systemid>Kyoto_Kyoto</systemid>
    <systemname>京都府京都市</systemname>
    <libkey>東山</libkey>
    <libid>102160</libid>
    <short>東山図書館</short>
    <formal>京都市東山図書館</formal>
    <url_pc>https://www2.kyotocitylib.jp/</url_pc>
    <address>京都府京都市東山区清水五丁目130-8 東山区総合庁舎南館2階</address>
    <pref>京都府</pref>
    <city>京都市</city>
    <post>605-0862</post>
    <tel>075-541-5455</tel>
    <geocode>135.776278,34.99668</geocode>
    <category>MEDIUM</category>
    <image/>
  </Library>
  <Library>
    <systemid>Kyoto_Kyoto</systemid>
    <systemname>京都府京都市</systemname>
    <libkey>洛西</libkey>
    <libid>102161</libid>
    <short>洛西図書館</short>
    <formal>京都市洛西図書館</formal>
    <url_pc>https://www2.kyotocitylib.jp/</url_pc>
    <address>京都府京都市西京区大原野東境谷町2丁目1-2 洛西総合庁舎1階</address>
    <pref>京都府</pref>
    <city>京都市</city>
    <post>610-1143</post>
    <tel>075-333-0577</tel>
    <geocode>135.674766,34.964356</geocode>
    <category>MEDIUM</category>
    <image/>
  </Library>
  <Library>
    <systemid>Kyoto_Kyoto</systemid>
    <systemname>京都府京都市</systemname>
    <libkey>移動</libkey>
    <libid>102162</libid>
    <short>こじか号</short>
    <formal>京都市移動図書館「こじか号」</formal>
    <url_pc>https://www2.kyotocitylib.jp/</url_pc>
    <address>京都府京都市中京区聚楽廻松下町9-2</address>
    <pref>京都府</pref>
    <city>京都市</city>
    <post>604-8401</post>
    <tel>075-801-4196</tel>
    <geocode>135.7384262,35.0189963</geocode>
    <category>BM</category>
    <image/>
  </Library>
  <Library>
    <systemid>Kyoto_Kyoto</systemid>
    <systemname>京都府京都市</systemname>
    <libkey>西京</libkey>
    <libid>102163</libid>
    <short>西京図書館</short>
    <formal>京都市西京図書館</formal>
    <url_pc>https://www2.kyotocitylib.jp/</url_pc>
    <address>京都府京都市西京区山田大吉見町20-3</address>
    <pref>京都府</pref>
    <city>京都市</city>
    <post>615-8236</post>
    <tel>075-392-5558</tel>
    <geocode>135.6905754,34.9812714</geocode>
    <category>MEDIUM</category>
    <image/>
  </Library>
  <Library>
    <systemid>Kyoto_Kyoto</systemid>
    <systemname>京都府京都市</systemname>
    <libkey>醍中</libkey>
    <libid>102164</libid>
    <short>醍醐中央図書館</short>
    <formal>京都市醍醐中央図書館</formal>
    <url_pc>https://www2.kyotocitylib.jp/</url_pc>
    <address>京都府京都市伏見区醍醐高畑町30-1 パセオ・ダイゴロー西館4階</address>
    <pref>京都府</pref>
    <city>京都市</city>
    <post>601-1375</post>
    <tel>075-575-2584</tel>
    <geocode>135.8103554,34.9508685</geocode>
    <category>MEDIUM</category>
    <image/>
  </Library>
  <Library>
    <systemid>Kyoto_Kyoto</systemid>
    <systemname>京都府京都市</systemname>
    <libkey>醍醐</libkey>
    <libid>102165</libid>
    <short>醍醐図書館</short>
    <formal>京都市醍醐図書館</formal>
    <url_pc>https://www2.kyotocitylib.jp/</url_pc>
    <address>京都府京都市伏見区石田西ノ坪1-2</address>
    <pref>京都府</pref>
    <city>京都市</city>
    <post>601-1436</post>
    <tel>075-572-0700</tel>
    <geocode>135.8009006,34.9386026</geocode>
    <category>MEDIUM</category>
    <image/>
  </Library>
  <Library>
    <systemid>Kyoto_Maizuru</systemid>
    <systemname>京都府舞鶴市</systemname>
    <libkey>東図書館</libkey>
    <libid>102166</libid>
    <short>東図書館</short>
    <formal>舞鶴市立東図書館</formal>
    <url_pc>https://ilisod001.apsel.jp/maizuru-lib/wopc/pc/pages/TopPage.jsp</url_pc>
    <address>京都府舞鶴市字溝尻25番地</address>
    <pref>京都府</pref>
    <city>舞鶴市</city>
    <post>625-0035</post>
    <tel>0773-62-0190</tel>
    <geocode>135.401446,35.4777996</geocode>
    <category>MEDIUM</category>
    <image/>
  </Library>
  <Library>
    <systemid>Kyoto_Maizuru</systemid>
    <systemname>京都府舞鶴市</systemname>
    <libkey>西図書館</libkey>
    <libid>102167</libid>
    <short>西図書館</short>
    <formal>舞鶴市立西図書館</formal>
    <url_pc>https://ilisod001.apsel.jp/maizuru-lib/wopc/pc/pages/TopPage.jsp</url_pc>
    <address>京都府舞鶴市字円満寺100番地の8</address>
    <pref>京都府</pref>
    <city>舞鶴市</city>
    <post>624-0854</post>
    <tel>0773-75-5406</tel>
    <geocode>135.3322195,35.4492994</geocode>
    <category>MEDIUM</category>
    <image/>
  </Library>
  <Library>
    <systemid>Kyoto_Miyazu</systemid>
    <systemname>京都府宮津市</systemname>
    <libkey>宮津市立図書館</libkey>
    <libid>102192</libid>
    <short>宮津市立図書館</short>
    <formal>宮津市立図書館</formal>
    <url_pc>http://www.city.miyazu.kyoto.jp/www/section/detail.jsp?id=77</url_pc>
    <address>京都府宮津市字浜町3012 宮津阪急ビル「ミップル」3F</address>
    <pref>京都府</pref>
    <city>宮津市</city>
    <post>626-8501</post>
    <tel>0772-22-2730</tel>
    <geocode>135.1935583,35.5391791</geocode>
    <category>MEDIUM</category>
    <image/>
  </Library>
  <Library>
    <systemid>Kyoto_Miyazu</systemid>
    <systemname>京都府宮津市</systemname>
    <libkey>移動図書館</libkey>
    <libid>121987</libid>
    <short>はまなす文庫</short>
    <formal>宮津市立図書館移動図書館「はまなす文庫」</formal>
    <url_pc>http://www.city.miyazu.kyoto.jp/www/section/detail.jsp?id=77</url_pc>
    <address>京都府宮津市字柳縄手3012 宮津阪急ビル「ミップル」3F</address>
    <pref>京都府</pref>
    <city>宮津市</city>
    <post>626-8501</post>
    <tel>0772-22-2730</tel>
    <geocode>135.1937443,35.5392525</geocode>
    <category>BM</category>
    <image/>
  </Library>
  <Library>
    <systemid>Kyoto_Muko</systemid>
    <systemname>京都府向日市</systemname>
    <libkey>向日市立図書館</libkey>
    <libid>102168</libid>
    <short>向日市立図書館</short>
    <formal>向日市立図書館</formal>
    <url_pc>http://www.library.muko.kyoto.jp/</url_pc>
    <address>京都府向日市寺戸町南垣内40-1</address>
    <pref>京都府</pref>
    <city>向日市</city>
    <post>617-0002</post>
    <tel>075-931-1181</tel>
    <geocode>135.699478,34.949160</geocode>
    <category>MEDIUM</category>
    <image/>
  </Library>
  <Library>
    <systemid>Kyoto_Nagaokakyo</systemid>
    <systemname>京都府長岡京市</systemname>
    <libkey>長岡京図書</libkey>
    <libid>102169</libid>
    <short>長岡京市立図書館</short>
    <formal>長岡京市立図書館</formal>
    <url_pc>https://www.lics-saas.nexs-service.jp/nagaokakyo/</url_pc>
    <address>京都府長岡京市天神四丁目1番1号</address>
    <pref>京都府</pref>
    <city>長岡京市</city>
    <post>617-0824</post>
    <tel>075-951-4646</tel>
    <geocode>135.688256,34.926483</geocode>
    <category>MEDIUM</category>
    <image/>
  </Library>
  <Library>
    <systemid>Kyoto_Nantan</systemid>
    <systemname>京都府南丹市</systemname>
    <libkey>中央館</libkey>
    <libid>102173</libid>
    <short>中央図書館</short>
    <formal>南丹市立中央図書館</formal>
    <url_pc>https://www.lics-saas.nexs-service.jp/nantan/</url_pc>
    <address>京都府南丹市園部町小桜町63</address>
    <pref>京都府</pref>
    <city>南丹市</city>
    <post>622-0004</post>
    <tel>0771-68-0080</tel>
    <geocode>135.471254,35.1066214</geocode>
    <category>MEDIUM</category>
    <image/>
  </Library>
  <Library>
    <systemid>Kyoto_Nantan</systemid>
    <systemname>京都府南丹市</systemname>
    <libkey>八木</libkey>
    <libid>102174</libid>
    <short>八木図書室</short>
    <formal>南丹市八木図書室</formal>
    <url_pc>https://www.lics-saas.nexs-service.jp/nantan/</url_pc>
    <address>京都府南丹市八木町八木東久保29-1</address>
    <pref>京都府</pref>
    <city>南丹市</city>
    <post>629-0198</post>
    <tel>0771-68-0027</tel>
    <geocode>135.532663,35.070742</geocode>
    <category>SMALL</category>
    <image/>
  </Library>
  <Library>
    <systemid>Kyoto_Nantan</systemid>
    <systemname>京都府南丹市</systemname>
    <libkey>日吉</libkey>
    <libid>102175</libid>
    <short>日吉図書室</short>
    <formal>南丹市日吉図書室</formal>
    <url_pc>https://www.lics-saas.nexs-service.jp/nantan/</url_pc>
    <address>京都府南丹市日吉町保野田長通り24</address>
    <pref>京都府</pref>
    <city>南丹市</city>
    <post>629-0301</post>
    <tel>0771-68-0036</tel>
    <geocode>135.489441,35.180394</geocode>
    <category>SMALL</category>
    <image/>
  </Library>
  <Library>
    <systemid>Kyoto_Nantan</systemid>
    <systemname>京都府南丹市</systemname>
    <libkey>美山</libkey>
    <libid>102176</libid>
    <short>美山図書室</short>
    <formal>南丹市美山図書室</formal>
    <url_pc>https://www.lics-saas.nexs-service.jp/nantan/</url_pc>
    <address>京都府南丹市美山町島島台51番地</address>
    <pref>京都府</pref>
    <city>南丹市</city>
    <post>601-0751</post>
    <tel>0771-68-0046</tel>
    <geocode>135.549394,35.271540</geocode>
    <category>SMALL</category>
    <image/>
  </Library>
  <Library>
    <systemid>Kyoto_Nantan</systemid>
    <systemname>京都府南丹市</systemname>
    <libkey>美山ＢＭ</libkey>
    <libid>102177</libid>
    <short>美山移動図書館</short>
    <formal>南丹市美山移動図書館</formal>
    <url_pc>https://www.lics-saas.nexs-service.jp/nantan/</url_pc>
    <address>京都府南丹市美山町島島台51番地</address>
    <pref>京都府</pref>
    <city>南丹市</city>
    <post>601-0751</post>
    <tel>0771-68-0046</tel>
    <geocode>135.5499196,35.2721142</geocode>
    <category>BM</category>
    <image/>
  </Library>
  <Library>
    <systemid>Kyoto_Nantan</systemid>
    <systemname>京都府南丹市</systemname>
    <libkey>興風</libkey>
    <libid>102178</libid>
    <short>日吉興風交流センター</short>
    <formal>南丹市日吉興風交流センター図書室</formal>
    <url_pc>https://www.lics-saas.nexs-service.jp/nantan/</url_pc>
    <address>京都府南丹市日吉町田原渕谷口25番地</address>
    <pref>京都府</pref>
    <city>南丹市</city>
    <post>629-0323</post>
    <tel>0771-73-0514</tel>
    <geocode>135.5198296,35.1903813</geocode>
    <category>SMALL</category>
    <image/>
  </Library>
  <Library>
    <systemid>Kyoto_Oyamazaki</systemid>
    <systemname>京都府大山崎町</systemname>
    <libkey>大山崎図書</libkey>
    <libid>102190</libid>
    <short>大山崎町中央公民館</short>
    <formal>大山崎町中央公民館図書室</formal>
    <url_pc>http://www.town.oyamazaki.kyoto.jp/annai/kyoikuiinkai/chuokominkan/tosyo/1108.html</url_pc>
    <address>京都府乙訓郡大山崎町字円明寺小字夏目26</address>
    <pref>京都府</pref>
    <city>乙訓郡大山崎町</city>
    <post>618-0091</post>
    <tel>075-957-1421</tel>
    <geocode>135.688341,34.90233</geocode>
    <category>SMALL</category>
    <image/>
  </Library>
  <Library>
    <systemid>Kyoto_Pref</systemid>
    <systemname>京都府立図書館</systemname>
    <libkey>府立図書館</libkey>
    <libid>102179</libid>
    <short>京都府立図書館</short>
    <formal>京都府立図書館</formal>
    <url_pc>http://www.library.pref.kyoto.jp/</url_pc>
    <address>京都府京都市左京区岡崎成勝寺町9</address>
    <pref>京都府</pref>
    <city>京都市</city>
    <post>606-8343</post>
    <tel>075-762-4655</tel>
    <geocode>135.7819699,35.0129668</geocode>
    <category>LARGE</category>
    <image/>
  </Library>
  <Library>
    <systemid>Kyoto_Seika</systemid>
    <systemname>京都府精華町</systemname>
    <libkey>図書館</libkey>
    <libid>102203</libid>
    <short>精華町立図書館</short>
    <formal>精華町立図書館</formal>
    <url_pc>https://www.town.seika.kyoto.jp/toshokan/index.html</url_pc>
    <address>京都府相楽郡精華町大字南稲八妻小字北尻70番地</address>
    <pref>京都府</pref>
    <city>相楽郡精華町</city>
    <post>619-0285</post>
    <tel>0774-95-1911</tel>
    <geocode>135.786093,34.760799</geocode>
    <category>MEDIUM</category>
    <image/>
  </Library>
  <Library>
    <systemid>Kyoto_Seika</systemid>
    <systemname>京都府精華町</systemname>
    <libkey>ＢＭ</libkey>
    <libid>110438</libid>
    <short>あおぞら号</short>
    <formal>精華町移動図書館車「あおぞら号・バーバパパ」</formal>
    <url_pc>https://www.town.seika.kyoto.jp/toshokan/index.html</url_pc>
    <address>京都府相楽郡精華町大字南稲八妻小字北尻70番地</address>
    <pref>京都府</pref>
    <city>相楽郡精華町</city>
    <post>619-0285</post>
    <tel>0774-95-1911</tel>
    <geocode>135.7856858,34.7608167</geocode>
    <category>BM</category>
    <image/>
  </Library>
  <Library>
    <systemid>Kyoto_Uji</systemid>
    <systemname>京都府宇治市</systemname>
    <libkey>中央図書館</libkey>
    <libid>102204</libid>
    <short>中央図書館</short>
    <formal>宇治市中央図書館</formal>
    <url_pc>https://www.city.uji.kyoto.jp/soshiki/10/</url_pc>
    <address>京都府宇治市折居台1丁目1番地</address>
    <pref>京都府</pref>
    <city>宇治市</city>
    <post>611-0023</post>
    <tel>0774-39-9256</tel>
    <geocode>135.804570,34.878973</geocode>
    <category>MEDIUM</category>
    <image/>
  </Library>
  <Library>
    <systemid>Kyoto_Uji</systemid>
    <systemname>京都府宇治市</systemname>
    <libkey>東宇治図書館</libkey>
    <libid>102207</libid>
    <short>東宇治図書館</short>
    <formal>宇治市東宇治図書館 </formal>
    <url_pc>https://www.city.uji.kyoto.jp/soshiki/10/</url_pc>
    <address>京都府宇治市五ヶ庄三番割36番地の5</address>
    <pref>京都府</pref>
    <city>宇治市</city>
    <post>611-0011</post>
    <tel>0774-39-9182</tel>
    <geocode>135.8035114,34.9165769</geocode>
    <category>MEDIUM</category>
    <image/>
  </Library>
  <Library>
    <systemid>Kyoto_Uji</systemid>
    <systemname>京都府宇治市</systemname>
    <libkey>西宇治図書館</libkey>
    <libid>102209</libid>
    <short>西宇治図書館</short>
    <formal>宇治市西宇治図書館</formal>
    <url_pc>https://www.city.uji.kyoto.jp/soshiki/10/</url_pc>
    <address>京都府宇治市小倉町山際63-1 西小倉地域福祉センター3階</address>
    <pref>京都府</pref>
    <city>宇治市</city>
    <post>611-0042</post>
    <tel>0774-39-9226</tel>
    <geocode>135.7754176,34.8885516</geocode>
    <category>MEDIUM</category>
    <image/>
  </Library>
  <Library>
    <systemid>Kyoto_Ujitawara</systemid>
    <systemname>京都府宇治田原町</systemname>
    <libkey>宇治田原</libkey>
    <libid>102191</libid>
    <short>宇治田原町立図書館</short>
    <formal>宇治田原町立図書館</formal>
    <url_pc>http://www.town.ujitawara.kyoto.jp/</url_pc>
    <address>京都府綴喜郡宇治田原町大字岩山小字沼尻46-1</address>
    <pref>京都府</pref>
    <city>綴喜郡宇治田原町</city>
    <post>610-0261</post>
    <tel>0774-88-5852</tel>
    <geocode>135.863087,34.85577</geocode>
    <category>MEDIUM</category>
    <image/>
  </Library>
  <Library>
    <systemid>Kyoto_Yawata</systemid>
    <systemname>京都府八幡市</systemname>
    <libkey>八幡市民図書館</libkey>
    <libid>102211</libid>
    <short>八幡市民図書館</short>
    <formal>八幡市立八幡市民図書館</formal>
    <url_pc>https://www3.city.yawata.kyoto.jp/TOSHOW/index.asp</url_pc>
    <address>京都府八幡市八幡菖蒲池11番地</address>
    <pref>京都府</pref>
    <city>八幡市</city>
    <post>614-8082</post>
    <tel>075-982-7322</tel>
    <geocode>135.704483,34.878096</geocode>
    <category>MEDIUM</category>
    <image/>
  </Library>
  <Library>
    <systemid>Kyoto_Yawata</systemid>
    <systemname>京都府八幡市</systemname>
    <libkey>男山市民図書館</libkey>
    <libid>102212</libid>
    <short>男山市民図書館</short>
    <formal>八幡市立男山市民図書館</formal>
    <url_pc>https://www3.city.yawata.kyoto.jp/TOSHOW/index.asp</url_pc>
    <address>京都府八幡市男山竹園2番地3</address>
    <pref>京都府</pref>
    <city>八幡市</city>
    <post>614-8376</post>
    <tel>075-982-4123</tel>
    <geocode>135.6971335,34.8559981</geocode>
    <category>MEDIUM</category>
    <image/>
  </Library>
  <Library>
    <systemid>Kyoto_Yosano</systemid>
    <systemname>京都府与謝野町</systemname>
    <libkey>与謝野町立図書館</libkey>
    <libid>102213</libid>
    <short>与謝野町立図書館</short>
    <formal>与謝野町立図書館</formal>
    <url_pc>https://ilisod001.apsel.jp/yosano-lib/wopc/pc/pages/TopPage.jsp</url_pc>
    <address>京都府与謝郡与謝野町字岩滝2271番地</address>
    <pref>京都府</pref>
    <city>与謝郡与謝野町</city>
    <post>629-2262</post>
    <tel>0772-46-2451</tel>
    <geocode>135.151158,35.563880</geocode>
    <category>MEDIUM</category>
    <image/>
  </Library>
  <Library>
    <systemid>Kyoto_Yosano</systemid>
    <systemname>京都府与謝野町</systemname>
    <libkey>加悦分室</libkey>
    <libid>102214</libid>
    <short>加悦分室</short>
    <formal>与謝野町立図書館加悦分室</formal>
    <url_pc>https://ilisod001.apsel.jp/yosano-lib/wopc/pc/pages/TopPage.jsp</url_pc>
    <address>京都府与謝郡与謝野町字加悦451-2</address>
    <pref>京都府</pref>
    <city>与謝郡与謝野町</city>
    <post>629-2403</post>
    <tel>0772-43-0376</tel>
    <geocode>135.0938532,35.5046979</geocode>
    <category>SMALL</category>
    <image/>
  </Library>
  <Library>
    <systemid>Kyoto_Yosano</systemid>
    <systemname>京都府与謝野町</systemname>
    <libkey>野田川分室</libkey>
    <libid>102215</libid>
    <short>野田川分室</short>
    <formal>与謝野町立野田川分室</formal>
    <url_pc>https://ilisod001.apsel.jp/yosano-lib/wopc/pc/pages/TopPage.jsp</url_pc>
    <address>京都府与謝郡与謝野町字四辻142-1</address>
    <pref>京都府</pref>
    <city>与謝郡与謝野町</city>
    <post>629-2312</post>
    <tel>0772-43-0087</tel>
    <geocode>135.1038404,35.5281645</geocode>
    <category>SMALL</category>
    <image/>
  </Library>
  <Library>
    <systemid>Special_Affrc</systemid>
    <systemname>農林水産関係試験研究機関総合目録</systemname>
    <libkey>森総研関西</libkey>
    <libid>113217</libid>
    <short>森林総合研究所(関西)</short>
    <formal>森林総合研究所関西支所図書室</formal>
    <url_pc>http://www.ffpri.affrc.go.jp/fsm/</url_pc>
    <address>京都府京都市伏見区桃山町永井久太郎68番地</address>
    <pref>京都府</pref>
    <city>京都市</city>
    <post>612-0855</post>
    <tel>075-611-1201</tel>
    <geocode>135.7721172,34.9407127</geocode>
    <category>SPECIAL</category>
    <image/>
  </Library>
  <Library>
    <systemid>Special_Khrri</systemid>
    <systemname>世界人権問題研究センター・人権図書室</systemname>
    <libkey>本館</libkey>
    <libid>122575</libid>
    <short>人権図書室</short>
    <formal>世界人権問題研究センター「人権図書室」</formal>
    <url_pc>http://khrri.or.jp/library/library.html</url_pc>
    <address>京都府京都市中京区天神山町290-1</address>
    <pref>京都府</pref>
    <city>京都市</city>
    <post>604-8221</post>
    <tel>075-231-2600</tel>
    <geocode>135.7577288,35.0051159</geocode>
    <category>SPECIAL</category>
    <image/>
  </Library>
  <Library>
    <systemid>Special_Matsushita</systemid>
    <systemname>松下資料館</systemname>
    <libkey>図書館</libkey>
    <libid>122938</libid>
    <short>松下資料館経営図書館</short>
    <formal>松下資料館経営図書館</formal>
    <url_pc>http://matsushita-library.jp/</url_pc>
    <address>京都府京都市南区西九条北ノ内町11 PHPビル3階</address>
    <pref>京都府</pref>
    <city>京都市</city>
    <post>601-8411</post>
    <tel>075-661-6640</tel>
    <geocode>135.7546397,34.9838603</geocode>
    <category>SPECIAL</category>
    <image/>
  </Library>
  <Library>
    <systemid>Special_Miyako_Eco</systemid>
    <systemname>京都市環境保全活動センター</systemname>
    <libkey>図書コーナー</libkey>
    <libid>113623</libid>
    <short>エコセン図書コーナー</short>
    <formal>京都市環境保全活動センター「京エコロジーセンター」図書コーナー</formal>
    <url_pc>http://www.miyako-eco.jp/ecocen/use/</url_pc>
    <address>京都府京都市伏見区深草池ノ内町13</address>
    <pref>京都府</pref>
    <city>京都市</city>
    <post>612-0031</post>
    <tel>075-641-0911</tel>
    <geocode>135.7661265,34.9559722</geocode>
    <category>SPECIAL</category>
    <image/>
  </Library>
  <Library>
    <systemid>Special_Momak</systemid>
    <systemname>京都国立近代美術館</systemname>
    <libkey>資料室</libkey>
    <libid>122284</libid>
    <short>京都国立近代美術館ライブラリー</short>
    <formal>京都国立近代美術館ライブラリー</formal>
    <url_pc>http://www.momak.go.jp/Japanese/library.html</url_pc>
    <address>京都府京都市左京区岡崎円勝寺町26-1</address>
    <pref>京都府</pref>
    <city>京都市</city>
    <post>606-8344</post>
    <tel>075-761-9617</tel>
    <geocode>135.781922,35.012386</geocode>
    <category>SPECIAL</category>
    <image/>
  </Library>
  <Library>
    <systemid>Special_Nichibun</systemid>
    <systemname>国際日本文化研究センター</systemname>
    <libkey>図書館</libkey>
    <libid>105857</libid>
    <short>国際日本文化研究センター</short>
    <formal>国際日本文化研究センター図書館</formal>
    <url_pc>http://library.nichibun.ac.jp/ja/</url_pc>
    <address>京都府京都市西京区御陵大枝山町3丁目2番地</address>
    <pref>京都府</pref>
    <city>京都市</city>
    <post>610-1192</post>
    <tel>075-335-2066</tel>
    <geocode>135.666961,34.988126</geocode>
    <category>SPECIAL</category>
    <image/>
  </Library>
  <Library>
    <systemid>Special_Wings_Kyoto</systemid>
    <systemname>京都市男女共同参画センター</systemname>
    <libkey>ウィングス</libkey>
    <libid>112898</libid>
    <short>ウィングス京都図書情報室</short>
    <formal>京都市男女共同参画センター「ウィングス京都」図書情報室</formal>
    <url_pc>https://www.wings-kyoto.jp/library/01us-01use/</url_pc>
    <address>京都府京都市中京区東洞院通六角下ル御射山町262</address>
    <pref>京都府</pref>
    <city>京都市</city>
    <post>604-8147</post>
    <tel>075-212-0606</tel>
    <geocode>135.761378,35.006857</geocode>
    <category>SPECIAL</category>
    <image/>
  </Library>
  <Library>
    <systemid>Tokyo_NDL</systemid>
    <systemname>国立国会図書館</systemname>
    <libkey>関西館</libkey>
    <libid>104107</libid>
    <short>関西館</short>
    <formal>国立国会図書館関西館</formal>
    <url_pc>http://www.ndl.go.jp/jp/kansai/index.html</url_pc>
    <address>京都府相楽郡精華町精華台8-1-3</address>
    <pref>京都府</pref>
    <city>相楽郡精華町</city>
    <post>619-0287</post>
    <tel>0774-98-1200</tel>
    <geocode>135.770133,34.743401</geocode>
    <category>LARGE</category>
    <image/>
  </Library>
  <Library>
    <systemid>Univ_Bukkyo</systemid>
    <systemname>佛教大学</systemname>
    <libkey>二条図書室</libkey>
    <libid>109621</libid>
    <short>二条図書室</short>
    <formal>佛教大学二条キャンパス図書室</formal>
    <url_pc>https://www.bukkyo-u.ac.jp/library/</url_pc>
    <address>京都府京都市中京区西ノ京東栂尾町7</address>
    <pref>京都府</pref>
    <city>京都市</city>
    <post>604-8418</post>
    <tel>075-491-2141 [佛教大学図書館]</tel>
    <geocode>135.742165,35.0100278</geocode>
    <category>UNIV</category>
    <image/>
  </Library>
  <Library>
    <systemid>Univ_Bukkyo</systemid>
    <systemname>佛教大学</systemname>
    <libkey>紫野</libkey>
    <libid>106190</libid>
    <short>図書館</short>
    <formal>佛教大学図書館</formal>
    <url_pc>http://www.bukkyo-u.ac.jp/facilities/library/</url_pc>
    <address>京都府京都市北区紫野北花ノ坊町96</address>
    <pref>京都府</pref>
    <city>京都市</city>
    <post>603-8301</post>
    <tel>075-491-2141</tel>
    <geocode>135.737899,35.043889</geocode>
    <category>UNIV</category>
    <image/>
  </Library>
  <Library>
    <systemid>Univ_Doshisha</systemid>
    <systemname>同志社大学</systemname>
    <libkey>ラーネッド記念図書館</libkey>
    <libid>106664</libid>
    <short>ラーネッド記念図書館</short>
    <formal>同志社大学ラーネッド記念図書館</formal>
    <url_pc>http://www.doshisha.ac.jp/library/</url_pc>
    <address>京都府京田辺市多々羅都谷1-3</address>
    <pref>京都府</pref>
    <city>京田辺市</city>
    <post>610-0394</post>
    <tel>0774-65-7240</tel>
    <geocode>135.770555,34.801241</geocode>
    <category>UNIV</category>
    <image/>
  </Library>
  <Library>
    <systemid>Univ_Doshisha</systemid>
    <systemname>同志社大学</systemname>
    <libkey>今出川図書館</libkey>
    <libid>106667</libid>
    <short>今出川図書館</short>
    <formal>同志社大学図書館今出川図書館</formal>
    <url_pc>http://www.doshisha.ac.jp/library/</url_pc>
    <address>京都府京都市上京区今出川通り烏丸東入</address>
    <pref>京都府</pref>
    <city>京都市</city>
    <post>602-8580</post>
    <tel>075-251-3980</tel>
    <geocode>135.759921,35.029623</geocode>
    <category>UNIV</category>
    <image/>
  </Library>
  <Library>
    <systemid>Univ_Doshisha</systemid>
    <systemname>同志社大学</systemname>
    <libkey>歴史資料館</libkey>
    <libid>120406</libid>
    <short>歴史資料館</short>
    <formal>同志社大学歴史資料館</formal>
    <url_pc>http://hmuseum.doshisha.ac.jp/</url_pc>
    <address>京都府京田辺市多々羅都谷1-3</address>
    <pref>京都府</pref>
    <city>京田辺市</city>
    <post>610-0394</post>
    <tel>0774-65-7255</tel>
    <geocode>135.771802,34.800304</geocode>
    <category>UNIV</category>
    <image/>
  </Library>
  <Library>
    <systemid>Univ_Doshisha_W</systemid>
    <systemname>同志社女子大学</systemname>
    <libkey>女今図</libkey>
    <libid>106665</libid>
    <short>女子大今出川図書館</short>
    <formal>同志社女子大学図書・情報センター今出川図書館</formal>
    <url_pc>http://www.dwc.doshisha.ac.jp/library/</url_pc>
    <address>京都府京都市上京区今出川通寺町西入</address>
    <pref>京都府</pref>
    <city>京都市</city>
    <post>602-0893</post>
    <tel>075-251-4145</tel>
    <geocode>135.759889,35.029588</geocode>
    <category>UNIV</category>
    <image/>
  </Library>
  <Library>
    <systemid>Univ_Doshisha_W</systemid>
    <systemname>同志社女子大学</systemname>
    <libkey>女田図</libkey>
    <libid>106666</libid>
    <short>女子大京田辺図書館</short>
    <formal>同志社女子大学京田辺図書館</formal>
    <url_pc>http://www.dwc.doshisha.ac.jp/library/</url_pc>
    <address>京都府京都府京田辺市興戸</address>
    <pref>京都府</pref>
    <city>京田辺市</city>
    <post>610-0395</post>
    <tel>0774-65-8481</tel>
    <geocode>135.770759,34.805052</geocode>
    <category>UNIV</category>
    <image/>
  </Library>
  <Library>
    <systemid>Univ_Hanazono</systemid>
    <systemname>花園大学</systemname>
    <libkey>図書館</libkey>
    <libid>110937</libid>
    <short>情報センター</short>
    <formal>花園大学情報センター（図書館）</formal>
    <url_pc>https://www.hanazono.ac.jp/about/humic/</url_pc>
    <address>京都府京都市中京区西ノ京壺ノ内町8-1</address>
    <pref>京都府</pref>
    <city>京都市</city>
    <post>604-8456</post>
    <tel>075-823-0592</tel>
    <geocode>135.726445,35.01719</geocode>
    <category>UNIV</category>
    <image/>
  </Library>
  <Library>
    <systemid>Univ_Kbu</systemid>
    <systemname>京都文教大学</systemname>
    <libkey>大学図書館[F館]</libkey>
    <libid>112775</libid>
    <short>大学図書館</short>
    <formal>京都文教大学図書館</formal>
    <url_pc>http://www.kbu.ac.jp/kbu/library/</url_pc>
    <address>京都府宇治市槙島町千足80番地 普照館1階</address>
    <pref>京都府</pref>
    <city>宇治市</city>
    <post>611-0041</post>
    <tel>0774-25-2489</tel>
    <geocode>135.7839083,34.9139201</geocode>
    <category>UNIV</category>
    <image/>
  </Library>
  <Library>
    <systemid>Univ_Kbu</systemid>
    <systemname>京都文教大学</systemname>
    <libkey>大学院図書室[J館]</libkey>
    <libid>114018</libid>
    <short>京都文教大学大学院図書室</short>
    <formal>京都文教大学大学院図書室</formal>
    <url_pc>http://www.kbu.ac.jp/kbu/library/</url_pc>
    <address>京都府宇治市槇島町千足80 常照館</address>
    <pref>京都府</pref>
    <city>宇治市</city>
    <post>611-0041</post>
    <tel>0774-25-2489</tel>
    <geocode>135.7840565,34.9151698</geocode>
    <category>UNIV</category>
    <image/>
  </Library>
  <Library>
    <systemid>Univ_Kbu</systemid>
    <systemname>京都文教大学</systemname>
    <libkey>短大図書館[S館]</libkey>
    <libid>113303</libid>
    <short>短大図書館</short>
    <formal>京都文教短期大学図書館</formal>
    <url_pc>http://www.kbu.ac.jp/kbu/library/index.htm</url_pc>
    <address>京都府宇治市槙島町千足80番地 至道館3階</address>
    <pref>京都府</pref>
    <city>宇治市</city>
    <post>611-0041</post>
    <tel>0774-25-2420</tel>
    <geocode>135.7845751,34.9145723</geocode>
    <category>UNIV</category>
    <image/>
  </Library>
  <Library>
    <systemid>Univ_Kcua</systemid>
    <systemname>京都市立芸術大学</systemname>
    <libkey>本館</libkey>
    <libid>109206</libid>
    <short>附属図書館</short>
    <formal>京都市立芸術大学附属図書館</formal>
    <url_pc>http://libmuse.kcua.ac.jp/lib/</url_pc>
    <address>京都府京都市西京区大枝沓掛町13-6</address>
    <pref>京都府</pref>
    <city>京都市</city>
    <post>610-1197</post>
    <tel>075-334-2233</tel>
    <geocode>135.6636992,34.9744442</geocode>
    <category>UNIV</category>
    <image/>
  </Library>
  <Library>
    <systemid>Univ_Kit</systemid>
    <systemname>京都工芸繊維大学</systemname>
    <libkey>図書館</libkey>
    <libid>105144</libid>
    <short>附属図書館</short>
    <formal>京都工芸繊維大学附属図書館</formal>
    <url_pc>http://www.lib.kit.ac.jp/</url_pc>
    <address>京都府京都市左京区松ヶ崎橋上町1番地</address>
    <pref>京都府</pref>
    <city>京都市</city>
    <post>606-8585</post>
    <tel>075-724-7191</tel>
    <geocode>135.783604,35.050082</geocode>
    <category>UNIV</category>
    <image/>
  </Library>
  <Library>
    <systemid>Univ_Koka</systemid>
    <systemname>京都光華女子大学</systemname>
    <libkey>本館</libkey>
    <libid>104777</libid>
    <short>図書館</short>
    <formal>京都光華女子大学図書館</formal>
    <url_pc>http://www.koka.ac.jp/toshokan/</url_pc>
    <address>京都府京都市右京区西京極葛野町38</address>
    <pref>京都府</pref>
    <city>京都市</city>
    <post>615-0882</post>
    <tel>075-325-5399</tel>
    <geocode>135.718525,34.996695</geocode>
    <category>UNIV</category>
    <image/>
  </Library>
  <Library>
    <systemid>Univ_Kpu</systemid>
    <systemname>歴彩館・京都府立大学・京都府立医科大学</systemname>
    <libkey>医大図書館</libkey>
    <libid>106508</libid>
    <short>附属図書館</short>
    <formal>京都府立医科大学附属図書館</formal>
    <url_pc>http://www.kpu-m.ac.jp/k/library/</url_pc>
    <address>京都府京都市上京区清和院口寺町東入中御霊町410</address>
    <pref>京都府</pref>
    <city>京都市</city>
    <post>602-0857</post>
    <tel>075-212-5400</tel>
    <geocode>135.768684,35.023756</geocode>
    <category>UNIV</category>
    <image/>
  </Library>
  <Library>
    <systemid>Univ_Kpu</systemid>
    <systemname>歴彩館・京都府立大学・京都府立医科大学</systemname>
    <libkey>医大教養図書室</libkey>
    <libid>106506</libid>
    <short>花園図書室</short>
    <formal>京都府立医科大学花園図書室</formal>
    <url_pc>http://www.kpu-m.ac.jp/k/library/</url_pc>
    <address>京都府京都市北区大将軍西鷹司町13-1</address>
    <pref>京都府</pref>
    <city>京都市</city>
    <post>603-8334</post>
    <tel>075-465-7630</tel>
    <geocode>135.727692,35.023446</geocode>
    <category>UNIV</category>
    <image/>
  </Library>
  <Library>
    <systemid>Univ_Kpu</systemid>
    <systemname>歴彩館・京都府立大学・京都府立医科大学</systemname>
    <libkey>府大図書館</libkey>
    <libid>105057</libid>
    <short>附属図書館</short>
    <formal>京都府立大学附属図書館</formal>
    <url_pc>http://www2.kpu.ac.jp/toshokan/toshokan.html</url_pc>
    <address>京都府京都市左京区下鴨半木町</address>
    <pref>京都府</pref>
    <city>京都市</city>
    <post>606-8522</post>
    <tel>075-703-5130</tel>
    <geocode>135.766307,35.046848</geocode>
    <category>UNIV</category>
    <image/>
  </Library>
  <Library>
    <systemid>Univ_Kpu</systemid>
    <systemname>歴彩館・京都府立大学・京都府立医科大学</systemname>
    <libkey>歴彩館</libkey>
    <libid>102180</libid>
    <short>京都府立京都学・歴彩館</short>
    <formal>京都府立京都学・歴彩館</formal>
    <url_pc>http://www.pref.kyoto.jp/shiryokan/</url_pc>
    <address>京都府京都市左京区下鴨半木町1-4</address>
    <pref>京都府</pref>
    <city>京都市</city>
    <post>606-0823</post>
    <tel>075-723-4833</tel>
    <geocode>135.7664316,35.0505685</geocode>
    <category>SPECIAL</category>
    <image/>
  </Library>
  <Library>
    <systemid>Univ_Kufs</systemid>
    <systemname>京都外国語大学</systemname>
    <libkey>図</libkey>
    <libid>107511</libid>
    <short>付属図書館</short>
    <formal>京都外国語大学付属図書館</formal>
    <url_pc>http://www.kufs.ac.jp/toshokan/</url_pc>
    <address>京都府京都市右京区西院笠目町6</address>
    <pref>京都府</pref>
    <city>京都市</city>
    <post>615-8558</post>
    <tel>075-322-6030</tel>
    <geocode>135.7191506,35.0043721</geocode>
    <category>UNIV</category>
    <image/>
  </Library>
  <Library>
    <systemid>Univ_Kufs</systemid>
    <systemname>京都外国語大学</systemname>
    <libkey>図分館</libkey>
    <libid>107683</libid>
    <short>アジア関係図書館</short>
    <formal>京都外国語大学付属図書館分館（アジア関係図書館）</formal>
    <url_pc>http://www.kufs.ac.jp/toshokan/</url_pc>
    <address>京都府京都市右京区西院笠目町6</address>
    <pref>京都府</pref>
    <city>京都市</city>
    <post>615-8558</post>
    <tel>075-322-6214</tel>
    <geocode>135.719205,35.004420</geocode>
    <category>UNIV</category>
    <image/>
  </Library>
  <Library>
    <systemid>Univ_Kyobi</systemid>
    <systemname>京都美術工芸大学</systemname>
    <libkey>図書館</libkey>
    <libid>121190</libid>
    <short>京都美術工芸大学図書館</short>
    <formal>京都美術工芸大学付属図書館</formal>
    <url_pc>https://sv1.opac.jp/aop/cgi-bin/index.cgi?LibId=164r5fr</url_pc>
    <address>京都府南丹市園部町小山東町二本松1-1</address>
    <pref>京都府</pref>
    <city>南丹市</city>
    <post>622-0041</post>
    <tel>075-525-1515 [大学]</tel>
    <geocode>135.4778148,35.1000889</geocode>
    <category>UNIV</category>
    <image/>
  </Library>
  <Library>
    <systemid>Univ_Kyoto</systemid>
    <systemname>京都大学</systemname>
    <libkey>アア研</libkey>
    <libid>105443</libid>
    <short>アフリカ地域研究資料センター</short>
    <formal>京都大学大学院アフリカ地域研究資料センター</formal>
    <url_pc>http://www.africa.kyoto-u.ac.jp/tosho.html</url_pc>
    <address>京都府京都市左京区吉田下阿達町46 アジア・アフリカ地域研究研究科共同研究棟2階206号室</address>
    <pref>京都府</pref>
    <city>京都市</city>
    <post>606-8501</post>
    <tel>075-753-7816</tel>
    <geocode>135.7728927,35.0213994</geocode>
    <category>UNIV</category>
    <image/>
  </Library>
  <Library>
    <systemid>Univ_Kyoto</systemid>
    <systemname>京都大学</systemname>
    <libkey>エネ科</libkey>
    <libid>106917</libid>
    <short>エネルギー科学研究科図書室</short>
    <formal>京都大学大学院エネルギー科学研究科図書室</formal>
    <url_pc>http://www.kulib.kyoto-u.ac.jp/enelib/</url_pc>
    <address>京都府京都市左京区吉田本町 工学部2号館4階417号室</address>
    <pref>京都府</pref>
    <city>京都市</city>
    <post>606-8501</post>
    <tel>075-753-3591</tel>
    <geocode>135.783110,35.025710</geocode>
    <category>UNIV</category>
    <image/>
  </Library>
  <Library>
    <systemid>Univ_Kyoto</systemid>
    <systemname>京都大学</systemname>
    <libkey>フィ森林</libkey>
    <libid>121878</libid>
    <short>京都大学フィールド科学教育研究センター森林系図書室</short>
    <formal>京都大学フィールド科学教育研究センター森林系図書室</formal>
    <url_pc>https://fserc.kyoto-u.ac.jp/libraryf/</url_pc>
    <address>京都府京都市左京区北白川追分町 農学部総合館1階 N179</address>
    <pref>京都府</pref>
    <city>京都市</city>
    <post>606-8502</post>
    <tel>075-753-6016</tel>
    <geocode>135.7843546,35.030468</geocode>
    <category>UNIV</category>
    <image/>
  </Library>
  <Library>
    <systemid>Univ_Kyoto</systemid>
    <systemname>京都大学</systemname>
    <libkey>人情セ</libkey>
    <libid>109547</libid>
    <short>東アジア人文情報学研究センター</short>
    <formal>京都大学人文科学研究所附属東アジア人文情報学研究センター図書室</formal>
    <url_pc>http://www.kita.zinbun.kyoto-u.ac.jp/library/</url_pc>
    <address>京都府京都市左京区北白川東小倉町47</address>
    <pref>京都府</pref>
    <city>京都市</city>
    <post>606-8265</post>
    <tel>075-753-6990</tel>
    <geocode>135.789792,35.030276</geocode>
    <category>UNIV</category>
    <image/>
  </Library>
  <Library>
    <systemid>Univ_Kyoto</systemid>
    <systemname>京都大学</systemname>
    <libkey>人文研</libkey>
    <libid>105402</libid>
    <short>人文科学研究所</short>
    <formal>京都大学人文科学研究所図書室</formal>
    <url_pc>http://www.kulib.kyoto-u.ac.jp/modules/newdb/detail.php?id=24</url_pc>
    <address>京都府京都市左京区吉田本町 総合研究4号館2階203号室</address>
    <pref>京都府</pref>
    <city>京都市</city>
    <post>606-8501</post>
    <tel>075-753-6909</tel>
    <geocode>135.782161,35.028262</geocode>
    <category>UNIV</category>
    <image/>
  </Library>
  <Library>
    <systemid>Univ_Kyoto</systemid>
    <systemname>京都大学</systemname>
    <libkey>医</libkey>
    <libid>105002</libid>
    <short>医学図書館</short>
    <formal>京都大学医学図書館</formal>
    <url_pc>http://www.kulib.kyoto-u.ac.jp/</url_pc>
    <address>京都府京都市左京区吉田近衛町</address>
    <pref>京都府</pref>
    <city>京都市</city>
    <post>606-8501</post>
    <tel>075-753-4313</tel>
    <geocode>135.777651,35.022038</geocode>
    <category>UNIV</category>
    <image/>
  </Library>
  <Library>
    <systemid>Univ_Kyoto</systemid>
    <systemname>京都大学</systemname>
    <libkey>医人健</libkey>
    <libid>121856</libid>
    <short>京都大学医学図書館人間健康科学系図書室</short>
    <formal>京都大学医学図書館人間健康科学系図書室</formal>
    <url_pc>http://www.lib.med.kyoto-u.ac.jp/hs/</url_pc>
    <address>京都府京都市左京区聖護院川原町53</address>
    <pref>京都府</pref>
    <city>京都市</city>
    <post>606-8507</post>
    <tel>075-751-3911</tel>
    <geocode>135.775008,35.019120</geocode>
    <category>UNIV</category>
    <image/>
  </Library>
  <Library>
    <systemid>Univ_Kyoto</systemid>
    <systemname>京都大学</systemname>
    <libkey>吉田南</libkey>
    <libid>104991</libid>
    <short>逍遙館</short>
    <formal>京都大学吉田南総合図書館「逍遥館」</formal>
    <url_pc>http://www.kulib.kyoto-u.ac.jp/yoshidasouthlib/</url_pc>
    <address>京都府京都市左京区吉田二本松町</address>
    <pref>京都府</pref>
    <city>京都市</city>
    <post>606-8501</post>
    <tel>075-753-6525</tel>
    <geocode>135.780571,35.023548</geocode>
    <category>UNIV</category>
    <image/>
  </Library>
  <Library>
    <systemid>Univ_Kyoto</systemid>
    <systemname>京都大学</systemname>
    <libkey>地域研</libkey>
    <libid>107994</libid>
    <short>地域研究統合情報センター</short>
    <formal>京都大学地域研究統合情報センター図書室</formal>
    <url_pc>http://www.cias.kyoto-u.ac.jp/library/</url_pc>
    <address>京都府京都市左京区吉田下阿達町46 稲盛財団記念館1階 117号室</address>
    <pref>京都府</pref>
    <city>京都市</city>
    <post>606-8501</post>
    <tel>075-753-9617</tel>
    <geocode>135.772496,35.021109</geocode>
    <category>UNIV</category>
    <image/>
  </Library>
  <Library>
    <systemid>Univ_Kyoto</systemid>
    <systemname>京都大学</systemname>
    <libkey>地環</libkey>
    <libid>106481</libid>
    <short>地球環境学堂図書室</short>
    <formal>京都大学大学院地球環境学堂図書室</formal>
    <url_pc>http://www.kulib.kyoto-u.ac.jp/modules/newdb/detail.php?id=43</url_pc>
    <address>京都府京都市左京区吉田本町 総合研究5号館1階</address>
    <pref>京都府</pref>
    <city>京都市</city>
    <post>606-8501</post>
    <tel>075-753-5631</tel>
    <geocode>135.7831674,35.0283073</geocode>
    <category>UNIV</category>
    <image/>
  </Library>
  <Library>
    <systemid>Univ_Kyoto</systemid>
    <systemname>京都大学</systemname>
    <libkey>基礎研</libkey>
    <libid>105013</libid>
    <short>基礎物理学研究所</short>
    <formal>京都大学基礎物理学研究所図書室</formal>
    <url_pc>http://www2.yukawa.kyoto-u.ac.jp/~library.oj/index.html</url_pc>
    <address>京都府京都市左京区北白川追分町 基礎物理学研究所新館3階</address>
    <pref>京都府</pref>
    <city>京都市</city>
    <post>606-8502</post>
    <tel>075-753-7007</tel>
    <geocode>135.785983,35.030820</geocode>
    <category>UNIV</category>
    <image/>
  </Library>
  <Library>
    <systemid>Univ_Kyoto</systemid>
    <systemname>京都大学</systemname>
    <libkey>宇治</libkey>
    <libid>105001</libid>
    <short>宇治分館</short>
    <formal>京都大学附属図書館宇治分館</formal>
    <url_pc>http://www.kulib.kyoto-u.ac.jp/</url_pc>
    <address>京都府京都府宇治市五ヶ庄 化研共同研究棟1階</address>
    <pref>京都府</pref>
    <city>宇治市</city>
    <post>611-0011</post>
    <tel>0774-38-3010</tel>
    <geocode>135.800742,34.910367</geocode>
    <category>UNIV</category>
    <image/>
  </Library>
  <Library>
    <systemid>Univ_Kyoto</systemid>
    <systemname>京都大学</systemname>
    <libkey>工吉化学</libkey>
    <libid>121873</libid>
    <short>京都大学工学部工業化学科図書室</short>
    <formal>京都大学工学部工業化学科図書室</formal>
    <url_pc>https://www.t.kyoto-u.ac.jp/lib/ja</url_pc>
    <address>京都府京都市左京区吉田本町  工学部総合校舎5階509号室</address>
    <pref>京都府</pref>
    <city>京都市</city>
    <post>606-8501</post>
    <tel>075-753-5556</tel>
    <geocode>135.7818676,35.0256645</geocode>
    <category>UNIV</category>
    <image/>
  </Library>
  <Library>
    <systemid>Univ_Kyoto</systemid>
    <systemname>京都大学</systemname>
    <libkey>工吉建築</libkey>
    <libid>105006</libid>
    <short>工学部建築系図書室</short>
    <formal>京都大学工学研究科・工学部建築系図書室（吉田キャンパス）</formal>
    <url_pc>http://www.archi.kyoto-u.ac.jp/~library/</url_pc>
    <address>京都府京都市左京区吉田本町 総合研究5号館</address>
    <pref>京都府</pref>
    <city>京都市</city>
    <post>606-8501</post>
    <tel>075-753-5048</tel>
    <geocode>135.7831674,35.0283073</geocode>
    <category>UNIV</category>
    <image/>
  </Library>
  <Library>
    <systemid>Univ_Kyoto</systemid>
    <systemname>京都大学</systemname>
    <libkey>工吉物理</libkey>
    <libid>121868</libid>
    <short>京都大学工学研究科・工学部物理系図書室（吉田キャンパス）</short>
    <formal>京都大学工学研究科・工学部物理系図書室（吉田キャンパス）</formal>
    <url_pc>https://www.t.kyoto-u.ac.jp/lib/ja</url_pc>
    <address>京都府京都市左京区吉田本町 工学部物理系校舎1階123号室</address>
    <pref>京都府</pref>
    <city>京都市</city>
    <post>606-8501</post>
    <tel>075-753-5187</tel>
    <geocode>135.782764,35.026009</geocode>
    <category>UNIV</category>
    <image/>
  </Library>
  <Library>
    <systemid>Univ_Kyoto</systemid>
    <systemname>京都大学</systemname>
    <libkey>工吉電気</libkey>
    <libid>121861</libid>
    <short>京都大学工学研究科・工学部電気系図書室（吉田キャンパス）</short>
    <formal>京都大学工学研究科・工学部電気系図書室（吉田キャンパス）</formal>
    <url_pc>https://www.s-ee.t.kyoto-u.ac.jp/ja/library</url_pc>
    <address>京都府京都市左京区吉田本町 工学部電気総合館4階</address>
    <pref>京都府</pref>
    <city>京都市</city>
    <post>606-8501</post>
    <tel>075-753-5360</tel>
    <geocode>135.7832415,35.0275773</geocode>
    <category>UNIV</category>
    <image/>
  </Library>
  <Library>
    <systemid>Univ_Kyoto</systemid>
    <systemname>京都大学</systemname>
    <libkey>工桂化学</libkey>
    <libid>121875</libid>
    <short>京都大学工学研究科化学系図書室</short>
    <formal>京都大学工学研究科化学系図書室</formal>
    <url_pc>https://www.t.kyoto-u.ac.jp/lib/ja</url_pc>
    <address>京都府京都市西京区京都大学桂 A2棟 地下1階 006号室</address>
    <pref>京都府</pref>
    <city>京都市</city>
    <post>615-8510</post>
    <tel>075-383-2581</tel>
    <geocode>135.6820365,34.979663</geocode>
    <category>UNIV</category>
    <image/>
  </Library>
  <Library>
    <systemid>Univ_Kyoto</systemid>
    <systemname>京都大学</systemname>
    <libkey>工桂地球</libkey>
    <libid>121867</libid>
    <short>京都大学工学研究科・工学部地球系図書室（桂キャンパス）</short>
    <formal>京都大学工学研究科・工学部地球系図書室（桂キャンパス）</formal>
    <url_pc>https://www.t.kyoto-u.ac.jp/lib/ja</url_pc>
    <address>京都府京都市西京区京都大学桂 C1棟 1F 143号室</address>
    <pref>京都府</pref>
    <city>京都市</city>
    <post>615-8540</post>
    <tel>075-383-3146</tel>
    <geocode>135.676957,34.983143</geocode>
    <category>UNIV</category>
    <image/>
  </Library>
  <Library>
    <systemid>Univ_Kyoto</systemid>
    <systemname>京都大学</systemname>
    <libkey>工桂建築</libkey>
    <libid>121880</libid>
    <short>京都大学工学研究科・工学部建築系図書室（桂キャンパス）</short>
    <formal>京都大学工学研究科・工学部建築系図書室（桂キャンパス）</formal>
    <url_pc>http://www.library.archi.kyoto-u.ac.jp/</url_pc>
    <address>京都府京都市西京区京都大学桂 C2棟 4F 411号室</address>
    <pref>京都府</pref>
    <city>京都市</city>
    <post>615-8540</post>
    <tel>075-383-2962</tel>
    <geocode>135.6774901,34.9836503</geocode>
    <category>UNIV</category>
    <image/>
  </Library>
  <Library>
    <systemid>Univ_Kyoto</systemid>
    <systemname>京都大学</systemname>
    <libkey>工桂物理</libkey>
    <libid>112395</libid>
    <short>工学部物理系図書室</short>
    <formal>京都大学工学研究科・工学部物理系図書室（桂キャンパス）</formal>
    <url_pc>http://www.t.kyoto-u.ac.jp/lib/ja</url_pc>
    <address>京都府京都市西京区京都大学桂 C3棟1F a1S04-1号室</address>
    <pref>京都府</pref>
    <city>京都市</city>
    <post>615-8540</post>
    <tel>075-383-3572</tel>
    <geocode>135.678194,34.983637</geocode>
    <category>UNIV</category>
    <image/>
  </Library>
  <Library>
    <systemid>Univ_Kyoto</systemid>
    <systemname>京都大学</systemname>
    <libkey>工桂電気</libkey>
    <libid>121877</libid>
    <short>京都大学工学研究科・工学部電気系図書室（桂キャンパス）</short>
    <formal>京都大学工学研究科・工学部電気系図書室（桂キャンパス）</formal>
    <url_pc>https://www.s-ee.t.kyoto-u.ac.jp/ja/library</url_pc>
    <address>京都府京都市西京区 京都大学 桂A1棟 2F 207号室</address>
    <pref>京都府</pref>
    <city>京都市</city>
    <post>615-8510</post>
    <tel>075-383-2344</tel>
    <geocode>135.6815537,34.9788748</geocode>
    <category>UNIV</category>
    <image/>
  </Library>
  <Library>
    <systemid>Univ_Kyoto</systemid>
    <systemname>京都大学</systemname>
    <libkey>情報学</libkey>
    <libid>105018</libid>
    <short>情報学研究科図書室</short>
    <formal>京都大学大学院情報学研究科図書室</formal>
    <url_pc>http://lib.i.kyoto-u.ac.jp/</url_pc>
    <address>京都府京都市左京区吉田本町 総合研究8号館4階428号室</address>
    <pref>京都府</pref>
    <city>京都市</city>
    <post>606-8501</post>
    <tel>075-753-5390</tel>
    <geocode>135.781860,35.026663</geocode>
    <category>UNIV</category>
    <image/>
  </Library>
  <Library>
    <systemid>Univ_Kyoto</systemid>
    <systemname>京都大学</systemname>
    <libkey>教育</libkey>
    <libid>104992</libid>
    <short>教育学部図書室</short>
    <formal>京都大学教育学研究科・教育学部図書室</formal>
    <url_pc>http://www.educ.kyoto-u.ac.jp/aboutus/library/</url_pc>
    <address>京都府京都市左京区吉田本町 教育学部本館1階西端111号室</address>
    <pref>京都府</pref>
    <city>京都市</city>
    <post>606-8501</post>
    <tel>075-753-3016</tel>
    <geocode>135.7848696,35.0279988</geocode>
    <category>UNIV</category>
    <image/>
  </Library>
  <Library>
    <systemid>Univ_Kyoto</systemid>
    <systemname>京都大学</systemname>
    <libkey>数理研</libkey>
    <libid>105008</libid>
    <short>数理解析研究所</short>
    <formal>京都大学数理解析研究所図書室</formal>
    <url_pc>http://www.kurims.kyoto-u.ac.jp/~library/Home.html</url_pc>
    <address>京都府京都市左京区北白川追分町 数理解析研究所3F</address>
    <pref>京都府</pref>
    <city>京都市</city>
    <post>606-8502</post>
    <tel>075-753-7223</tel>
    <geocode>135.785821,35.030364</geocode>
    <category>UNIV</category>
    <image/>
  </Library>
  <Library>
    <systemid>Univ_Kyoto</systemid>
    <systemname>京都大学</systemname>
    <libkey>文</libkey>
    <libid>104994</libid>
    <short>文学研究科図書館</short>
    <formal>京都大学文学研究科図書館</formal>
    <url_pc>http://www.kulib.kyoto-u.ac.jp/</url_pc>
    <address>京都府京都市左京区吉田本町</address>
    <pref>京都府</pref>
    <city>京都市</city>
    <post>606-8501</post>
    <tel>075-753-2715</tel>
    <geocode>135.781816,35.027331</geocode>
    <category>UNIV</category>
    <image/>
  </Library>
  <Library>
    <systemid>Univ_Kyoto</systemid>
    <systemname>京都大学</systemname>
    <libkey>東南ア</libkey>
    <libid>105311</libid>
    <short>東南アジア研究所</short>
    <formal>京都大学東南アジア研究所図書室</formal>
    <url_pc>http://www.cseas.kyoto-u.ac.jp/library/</url_pc>
    <address>京都府京都市左京区吉田下阿達町46</address>
    <pref>京都府</pref>
    <city>京都市</city>
    <post>606-8501</post>
    <tel>075-753-7306</tel>
    <geocode>135.772705,35.021007</geocode>
    <category>UNIV</category>
    <image/>
  </Library>
  <Library>
    <systemid>Univ_Kyoto</systemid>
    <systemname>京都大学</systemname>
    <libkey>法</libkey>
    <libid>105037</libid>
    <short>法学部図書室</short>
    <formal>京都大学法学部図書室</formal>
    <url_pc>http://www.kulib.kyoto-u.ac.jp/lawlib/lawlib-j.html</url_pc>
    <address>京都府京都市左京区吉田本町 法経済学部北館2階</address>
    <pref>京都府</pref>
    <city>京都市</city>
    <post>606-8501</post>
    <tel>075-753-3114</tel>
    <geocode>135.780629,35.027401</geocode>
    <category>UNIV</category>
    <image/>
  </Library>
  <Library>
    <systemid>Univ_Kyoto</systemid>
    <systemname>京都大学</systemname>
    <libkey>理中央</libkey>
    <libid>104996</libid>
    <short>理学部中央図書室</short>
    <formal>京都大学理学研究科・理学部中央図書室</formal>
    <url_pc>http://www.sci.kyoto-u.ac.jp/lib/</url_pc>
    <address>京都府京都市左京区北白川追分町 理学部6号館1階</address>
    <pref>京都府</pref>
    <city>京都市</city>
    <post>606-8502</post>
    <tel>075-753-3622</tel>
    <geocode>135.782833,35.029411</geocode>
    <category>UNIV</category>
    <image/>
  </Library>
  <Library>
    <systemid>Univ_Kyoto</systemid>
    <systemname>京都大学</systemname>
    <libkey>理化学</libkey>
    <libid>121876</libid>
    <short>京都大学理学研究科・理学部化学専攻化学教室図書室</short>
    <formal>京都大学理学研究科・理学部化学専攻化学教室図書室</formal>
    <url_pc>http://kuchem.kyoto-u.ac.jp/tosho/</url_pc>
    <address>京都府京都市左京区北白川追分町 理学部6号館1階159号室</address>
    <pref>京都府</pref>
    <city>京都市</city>
    <post>606-8502</post>
    <tel>075-753-3966</tel>
    <geocode>135.7829822,35.0295074</geocode>
    <category>UNIV</category>
    <image/>
  </Library>
  <Library>
    <systemid>Univ_Kyoto</systemid>
    <systemname>京都大学</systemname>
    <libkey>理宇宙</libkey>
    <libid>122119</libid>
    <short>宇宙物理学教室図書室</short>
    <formal>京都大学理学研究科・理学部物理学・宇宙物理学専攻宇宙物理学教室図書室</formal>
    <url_pc>http://www.kusastro.kyoto-u.ac.jp/library/tosho.html</url_pc>
    <address>京都府京都市左京区北白川追分町理学4号館4階</address>
    <pref>京都府</pref>
    <city>京都市</city>
    <post>606-8502</post>
    <tel>075-753-3900</tel>
    <geocode>135.7832572,35.0308161</geocode>
    <category>UNIV</category>
    <image/>
  </Library>
  <Library>
    <systemid>Univ_Kyoto</systemid>
    <systemname>京都大学</systemname>
    <libkey>理数学</libkey>
    <libid>121862</libid>
    <short>京都大学理学研究科・理学部数学・数理解析専攻 数学教室図書室</short>
    <formal>京都大学理学研究科・理学部数学・数理解析専攻 数学教室図書室</formal>
    <url_pc>https://www.math.kyoto-u.ac.jp/library/</url_pc>
    <address>京都府京都市左京区北白川追分町 理学部3号館1F</address>
    <pref>京都府</pref>
    <city>京都市</city>
    <post>606-8502</post>
    <tel>075-753-3703</tel>
    <geocode>135.7831853,35.0302251</geocode>
    <category>UNIV</category>
    <image/>
  </Library>
  <Library>
    <systemid>Univ_Kyoto</systemid>
    <systemname>京都大学</systemname>
    <libkey>理物理</libkey>
    <libid>121866</libid>
    <short>京都大学理学研究科・理学部物理学・宇宙物理学専攻物理学教室図書室</short>
    <formal>京都大学理学研究科・理学部物理学・宇宙物理学専攻物理学教室図書室</formal>
    <url_pc>http://www2.scphys.kyoto-u.ac.jp/library/</url_pc>
    <address>京都府京都市左京区北白川追分町 理学5号館4階419号室</address>
    <pref>京都府</pref>
    <city>京都市</city>
    <post>606-8502</post>
    <tel>075-753-3803</tel>
    <geocode>135.7838342,35.0315984</geocode>
    <category>UNIV</category>
    <image/>
  </Library>
  <Library>
    <systemid>Univ_Kyoto</systemid>
    <systemname>京都大学</systemname>
    <libkey>理生物</libkey>
    <libid>121885</libid>
    <short>京都大学理学研究科・理学部生物科学専攻図書室</short>
    <formal>京都大学理学研究科・理学部生物科学専攻図書室</formal>
    <url_pc>http://www.biol.sci.kyoto-u.ac.jp/jpn/lib/</url_pc>
    <address>京都府京都市左京区北白川追分町 理学部2号館1階108号室</address>
    <pref>京都府</pref>
    <city>京都市</city>
    <post>606-8502</post>
    <tel>075-753-4082</tel>
    <geocode>135.782748,35.028974</geocode>
    <category>UNIV</category>
    <image/>
  </Library>
  <Library>
    <systemid>Univ_Kyoto</systemid>
    <systemname>京都大学</systemname>
    <libkey>経済</libkey>
    <libid>105012</libid>
    <short>経済学部図書室</short>
    <formal>京都大学大学院経済学研究科・経済学部図書室</formal>
    <url_pc>http://www.econ.kyoto-u.ac.jp/library/</url_pc>
    <address>京都府京都市左京区吉田本町 法経済学部北館1階</address>
    <pref>京都府</pref>
    <city>京都市</city>
    <post>606-8501</post>
    <tel>075-753-3412</tel>
    <geocode>135.780434,35.027217</geocode>
    <category>UNIV</category>
    <image/>
  </Library>
  <Library>
    <systemid>Univ_Kyoto</systemid>
    <systemname>京都大学</systemname>
    <libkey>経研</libkey>
    <libid>106971</libid>
    <short>経済研究所</short>
    <formal>京都大学経済研究所図書室</formal>
    <url_pc>http://www.kier.kyoto-u.ac.jp/~library/</url_pc>
    <address>京都府京都市左京区吉田本町 経済研究所本館2階</address>
    <pref>京都府</pref>
    <city>京都市</city>
    <post>606-8501</post>
    <tel>075-753-7109</tel>
    <geocode>135.779194,35.026321</geocode>
    <category>UNIV</category>
    <image/>
  </Library>
  <Library>
    <systemid>Univ_Kyoto</systemid>
    <systemname>京都大学</systemname>
    <libkey>経資セ</libkey>
    <libid>120037</libid>
    <short>経済学研究科・経済学部経済資料センター</short>
    <formal>京都大学経済学研究科・経済学部経済資料センター</formal>
    <url_pc>http://www.kulib.kyoto-u.ac.jp/newdb/12141</url_pc>
    <address>京都府京都市左京区吉田本町 法経済学部東館地下1階</address>
    <pref>京都府</pref>
    <city>京都市</city>
    <post>606-8501</post>
    <tel>075-753-3416</tel>
    <geocode>135.781196,35.027118</geocode>
    <category>UNIV</category>
    <image/>
  </Library>
  <Library>
    <systemid>Univ_Kyoto</systemid>
    <systemname>京都大学</systemname>
    <libkey>薬</libkey>
    <libid>105127</libid>
    <short>薬学部図書室</short>
    <formal>京都大学大学院薬学研究科・薬学部図書室</formal>
    <url_pc>http://www.pharm.kyoto-u.ac.jp/tosho/</url_pc>
    <address>京都府京都市左京区吉田下阿達町46-29 薬学部1F</address>
    <pref>京都府</pref>
    <city>京都市</city>
    <post>606-8501</post>
    <tel>075-753-4595</tel>
    <geocode>135.7748335,35.0214746</geocode>
    <category>UNIV</category>
    <image/>
  </Library>
  <Library>
    <systemid>Univ_Kyoto</systemid>
    <systemname>京都大学</systemname>
    <libkey>農</libkey>
    <libid>105448</libid>
    <short>農学部図書室</short>
    <formal>京都大学農学研究科・農学部図書室</formal>
    <url_pc>http://www.agril.kais.kyoto-u.ac.jp/index.html</url_pc>
    <address>京都府京都市左京区北白川追分町 農学部総合館2階 C-208</address>
    <pref>京都府</pref>
    <city>京都市</city>
    <post>606-8502</post>
    <tel>075-753-6016</tel>
    <geocode>135.784362,35.030479</geocode>
    <category>UNIV</category>
    <image/>
  </Library>
  <Library>
    <systemid>Univ_Kyoto</systemid>
    <systemname>京都大学</systemname>
    <libkey>農生経</libkey>
    <libid>121883</libid>
    <short>京都大学農学研究科生物資源経済学専攻司書室</short>
    <formal>京都大学農学研究科生物資源経済学専攻司書室</formal>
    <url_pc>http://www.kulib.kyoto-u.ac.jp/newdb/12135</url_pc>
    <address>京都府京都市左京区北白川追分町 農学部総合館 E-121室</address>
    <pref>京都府</pref>
    <city>京都市</city>
    <post>606-8502</post>
    <tel>075-753-6201</tel>
    <geocode>135.7843546,35.030468</geocode>
    <category>UNIV</category>
    <image/>
  </Library>
  <Library>
    <systemid>Univ_Kyoto</systemid>
    <systemname>京都大学</systemname>
    <libkey>附図</libkey>
    <libid>104998</libid>
    <short>附属図書館</short>
    <formal>京都大学附属図書館</formal>
    <url_pc>http://www.kulib.kyoto-u.ac.jp/</url_pc>
    <address>京都府京都市左京区吉田本町</address>
    <pref>京都府</pref>
    <city>京都市</city>
    <post>606-8501</post>
    <tel>075-753-2632</tel>
    <geocode>135.779584,35.026513</geocode>
    <category>UNIV</category>
    <image/>
  </Library>
  <Library>
    <systemid>Univ_Kyotogakuen</systemid>
    <systemname>京都先端科学大学</systemname>
    <libkey>亀岡本館</libkey>
    <libid>105222</libid>
    <short>図書館</short>
    <formal>京都先端科学大学図書館</formal>
    <url_pc>https://www.kuas.ac.jp/about/facility/library</url_pc>
    <address>京都府亀岡市曽我部町南条大谷1-1</address>
    <pref>京都府</pref>
    <city>亀岡市</city>
    <post>621-8555</post>
    <tel>0771-29-2292</tel>
    <geocode>135.553747,34.993854</geocode>
    <category>UNIV</category>
    <image/>
  </Library>
  <Library>
    <systemid>Univ_Kyoto_Art</systemid>
    <systemname>京都芸術大学</systemname>
    <libkey>本館</libkey>
    <libid>104780</libid>
    <short>芸術文化情報センター</short>
    <formal>京都芸術大学芸術文化情報センター</formal>
    <url_pc>http://acic.kyoto-art.ac.jp/</url_pc>
    <address>京都府京都市左京区北白川瓜生山2-116</address>
    <pref>京都府</pref>
    <city>京都市</city>
    <post>606-8271</post>
    <tel>075-791-9122</tel>
    <geocode>135.7923661,35.0368313</geocode>
    <category>UNIV</category>
    <image/>
  </Library>
  <Library>
    <systemid>Univ_Kyoto_Econ</systemid>
    <systemname>京都経済短期大学</systemname>
    <libkey>図書館</libkey>
    <libid>122267</libid>
    <short>京都経済短期大学図書館</short>
    <formal>京都経済短期大学図書館</formal>
    <url_pc>https://www.kyoto-econ.ac.jp/about/about-library/</url_pc>
    <address>京都府京都市西京区大枝東長町3-1</address>
    <pref>京都府</pref>
    <city>京都市</city>
    <post>610-1195</post>
    <tel>075-331-3159</tel>
    <geocode>135.679520,34.971154</geocode>
    <category>UNIV</category>
    <image/>
  </Library>
  <Library>
    <systemid>Univ_Kyoto_Ed</systemid>
    <systemname>京都教育大学</systemname>
    <libkey>図書館</libkey>
    <libid>105860</libid>
    <short>附属図書館</short>
    <formal>京都教育大学附属図書館</formal>
    <url_pc>http://lib1.kyokyo-u.ac.jp/</url_pc>
    <address>京都府京都市伏見区深草藤森町1</address>
    <pref>京都府</pref>
    <city>京都市</city>
    <post>612-8522</post>
    <tel>075-644-8179</tel>
    <geocode>135.774453,34.950100</geocode>
    <category>UNIV</category>
    <image/>
  </Library>
  <Library>
    <systemid>Univ_Kyoto_Phu</systemid>
    <systemname>京都薬科大学</systemname>
    <libkey>図書館</libkey>
    <libid>107506</libid>
    <short>図書館</short>
    <formal>京都薬科大学図書館</formal>
    <url_pc>https://www.kyoto-phu.ac.jp/library/</url_pc>
    <address>京都府京都市山科区御陵中内町5</address>
    <pref>京都府</pref>
    <city>京都市</city>
    <post>607-8414</post>
    <tel>075-595-4618</tel>
    <geocode>135.810472,34.990547</geocode>
    <category>UNIV</category>
    <image/>
  </Library>
  <Library>
    <systemid>Univ_Kyoto_Seika</systemid>
    <systemname>京都精華大学</systemname>
    <libkey>本館</libkey>
    <libid>104993</libid>
    <short>情報館</short>
    <formal>京都精華大学情報館</formal>
    <url_pc>http://johokan.kyoto-seika.ac.jp/index.php?event/8</url_pc>
    <address>京都府京都市左京区岩倉木野町137</address>
    <pref>京都府</pref>
    <city>京都市</city>
    <post>606-8588</post>
    <tel>075-702-5137</tel>
    <geocode>135.769385,35.073272</geocode>
    <category>UNIV</category>
    <image/>
  </Library>
  <Library>
    <systemid>Univ_Kyoto_Su</systemid>
    <systemname>京都産業大学</systemname>
    <libkey>図書館</libkey>
    <libid>110174</libid>
    <short>図書館</short>
    <formal>京都産業大学図書館</formal>
    <url_pc>http://www.kyoto-su.ac.jp/lib/</url_pc>
    <address>京都府京都市北区上賀茂本山</address>
    <pref>京都府</pref>
    <city>京都市</city>
    <post>603-8555</post>
    <tel>075-705-1446</tel>
    <geocode>135.756081,35.070231</geocode>
    <category>UNIV</category>
    <image/>
  </Library>
  <Library>
    <systemid>Univ_Kyoto_Wu</systemid>
    <systemname>京都女子大学</systemname>
    <libkey>図書館</libkey>
    <libid>105306</libid>
    <short>図書館</short>
    <formal>京都女子大学・京都女子大学短期大学部図書館</formal>
    <url_pc>http://www3.kyoto-wu.ac.jp/library/</url_pc>
    <address>京都府京都市東山区今熊野北日吉町35番地 E校舎</address>
    <pref>京都府</pref>
    <city>京都市</city>
    <post>605-8501</post>
    <tel>075-531-7070</tel>
    <geocode>135.7791924,34.9895136</geocode>
    <category>UNIV</category>
    <image/>
  </Library>
  <Library>
    <systemid>Univ_Maizuru_Ct</systemid>
    <systemname>舞鶴工業高等専門学校</systemname>
    <libkey>図書館</libkey>
    <libid>108532</libid>
    <short>図書館</short>
    <formal>舞鶴工業高等専門学校図書館</formal>
    <url_pc>https://www.maizuru-ct.ac.jp/facilities/library/</url_pc>
    <address>京都府舞鶴市字白屋234番地</address>
    <pref>京都府</pref>
    <city>舞鶴市</city>
    <post>625-8511</post>
    <tel>0773-62-8863</tel>
    <geocode>135.4397009,35.4965117</geocode>
    <category>UNIV</category>
    <image/>
  </Library>
  <Library>
    <systemid>Univ_Meiji_U</systemid>
    <systemname>明治国際医療大学</systemname>
    <libkey>図書館</libkey>
    <libid>109488</libid>
    <short>附属図書館</short>
    <formal>明治国際医療大学附属図書館</formal>
    <url_pc>http://www.meiji-u.ac.jp/toshokan/</url_pc>
    <address>京都府南丹市日吉町保野田ヒノ谷6-1</address>
    <pref>京都府</pref>
    <city>南丹市</city>
    <post>629-0392</post>
    <tel>0771-72-1181</tel>
    <geocode>135.491481,35.181263</geocode>
    <category>UNIV</category>
    <image/>
  </Library>
  <Library>
    <systemid>Univ_Notredame</systemid>
    <systemname>京都ノートルダム女子大学</systemname>
    <libkey>本館</libkey>
    <libid>104701</libid>
    <short>図書館情報センター</short>
    <formal>京都ノートルダム女子大学図書館情報センター</formal>
    <url_pc>http://nais.notredame.ac.jp/lib/</url_pc>
    <address>京都府京都市左京区下鴨南野々神町1番地</address>
    <pref>京都府</pref>
    <city>京都市</city>
    <post>606-0847</post>
    <tel>075-706-3751</tel>
    <geocode>135.7724729,35.0504213</geocode>
    <category>UNIV</category>
    <image/>
  </Library>
  <Library>
    <systemid>Univ_Otani</systemid>
    <systemname>大谷大学</systemname>
    <libkey>図書館</libkey>
    <libid>109625</libid>
    <short>図書館</short>
    <formal>大谷大学図書館</formal>
    <url_pc>http://www.otani.ac.jp/kyo_kikan/library/</url_pc>
    <address>京都府京都市北区小山上総町</address>
    <pref>京都府</pref>
    <city>京都市</city>
    <post>603-8143</post>
    <tel>075-411-8123</tel>
    <geocode>135.758843,35.042988</geocode>
    <category>UNIV</category>
    <image/>
  </Library>
  <Library>
    <systemid>Univ_Ritsumei</systemid>
    <systemname>立命館大学</systemname>
    <libkey>国際平和ミュージアム</libkey>
    <libid>120793</libid>
    <short>国際平和ミュージアム</short>
    <formal>立命館大学国際平和ミュージアム国際平和メディア資料室</formal>
    <url_pc>http://www.ritsumei.ac.jp/mng/er/wp-museum/</url_pc>
    <address>京都府京都市北区等持院北町56-1</address>
    <pref>京都府</pref>
    <city>京都市</city>
    <post>603-8577</post>
    <tel>075-465-8151</tel>
    <geocode>135.727346,35.033696</geocode>
    <category>UNIV</category>
    <image/>
  </Library>
  <Library>
    <systemid>Univ_Ritsumei</systemid>
    <systemname>立命館大学</systemname>
    <libkey>平井嘉一郎記念図書館</libkey>
    <libid>105735</libid>
    <short>平井嘉一郎記念図書館</short>
    <formal>平井嘉一郎記念図書館</formal>
    <url_pc>http://www.ritsumei.ac.jp/acd/mr/lib/</url_pc>
    <address>京都府京都市北区等持院北町56−1</address>
    <pref>京都府</pref>
    <city>京都市</city>
    <post>603-8577</post>
    <tel>075-465-8217</tel>
    <geocode>135.725223,35.034232</geocode>
    <category>UNIV</category>
    <image/>
  </Library>
  <Library>
    <systemid>Univ_Ritsumei</systemid>
    <systemname>立命館大学</systemname>
    <libkey>朱雀リサーチライブラリー</libkey>
    <libid>105740</libid>
    <short>朱雀リサーチライブラリー</short>
    <formal>立命館大学朱雀リサーチライブラリー</formal>
    <url_pc>http://www.ritsumei.ac.jp/acd/mr/lib/</url_pc>
    <address>京都府京都市中京区西ノ京朱雀町1番地</address>
    <pref>京都府</pref>
    <city>京都市</city>
    <post>604-8520</post>
    <tel>075-813-8257</tel>
    <geocode>135.742174,35.009248</geocode>
    <category>UNIV</category>
    <image/>
  </Library>
  <Library>
    <systemid>Univ_Ryukoku</systemid>
    <systemname>龍谷大学</systemname>
    <libkey>大宮</libkey>
    <libid>106329</libid>
    <short>大宮図書館</short>
    <formal>龍谷大学大宮図書館</formal>
    <url_pc>https://library.ryukoku.ac.jp/</url_pc>
    <address>京都府京都市下京区猪熊通七条上る大工町125−1</address>
    <pref>京都府</pref>
    <city>京都市</city>
    <post>600-8268</post>
    <tel>075-343-3311</tel>
    <geocode>135.7496451,34.9906297</geocode>
    <category>UNIV</category>
    <image/>
  </Library>
  <Library>
    <systemid>Univ_Ryukoku</systemid>
    <systemname>龍谷大学</systemname>
    <libkey>深草</libkey>
    <libid>106188</libid>
    <short>深草図書館</short>
    <formal>龍谷大学深草図書館</formal>
    <url_pc>https://library.ryukoku.ac.jp/</url_pc>
    <address>京都府京都市伏見区深草塚本町67</address>
    <pref>京都府</pref>
    <city>京都市</city>
    <post>612-8577</post>
    <tel>075-645-2564</tel>
    <geocode>135.767099,34.963833</geocode>
    <category>UNIV</category>
    <image/>
  </Library>
  <Library>
    <systemid>Univ_Seibi_U</systemid>
    <systemname>福知山公立大学</systemname>
    <libkey>本館</libkey>
    <libid>107904</libid>
    <short>メディアセンター</short>
    <formal>福知山市立公立大学メディアセンター</formal>
    <url_pc>http://www.fukuchiyama.ac.jp/associated_organization/media_center/media_center01</url_pc>
    <address>京都府福知山市堀3370</address>
    <pref>京都府</pref>
    <city>福知山市</city>
    <post>620-0886</post>
    <tel>0773-24-7100</tel>
    <geocode>135.128595,35.284468</geocode>
    <category>UNIV</category>
    <image/>
  </Library>
  <Library>
    <systemid>Univ_Shuchiin</systemid>
    <systemname>種智院大学</systemname>
    <libkey>図書館</libkey>
    <libid>106449</libid>
    <short>図書館</short>
    <formal>種智院大学図書館</formal>
    <url_pc>http://www.shuchiin.ac.jp/about/libe.html</url_pc>
    <address>京都府京都市伏見区向島西定請70</address>
    <pref>京都府</pref>
    <city>京都市</city>
    <post>612-8156</post>
    <tel>075-604-5707</tel>
    <geocode>135.7657898,34.9138154</geocode>
    <category>UNIV</category>
    <image/>
  </Library>
  <Library>
    <systemid>Univ_Tachibana</systemid>
    <systemname>京都橘大学</systemname>
    <libkey>図書館</libkey>
    <libid>109632</libid>
    <short>図書館</short>
    <formal>京都橘大学図書館</formal>
    <url_pc>http://www.tachibana-u.ac.jp/library/index.html</url_pc>
    <address>京都府京都市山科区大宅山田町34</address>
    <pref>京都府</pref>
    <city>京都市</city>
    <post>607-8175</post>
    <tel>075-574-4118</tel>
    <geocode>135.826605,34.967765</geocode>
    <category>UNIV</category>
    <image/>
  </Library>
  <Library>
    <systemid>Univ_Taiwa</systemid>
    <systemname>キャリエールホテル旅行専門学校</systemname>
    <libkey>キャリ校</libkey>
    <libid>108325</libid>
    <short>情報ライブラリー</short>
    <formal>キャリエールホテル旅行専門学校情報ライブラリー</formal>
    <url_pc>http://library.taiwa.ac.jp/opac4/opac/Top</url_pc>
    <address>京都府京都市中京区河原町三条上ル</address>
    <pref>京都府</pref>
    <city>京都市</city>
    <post>604-8006</post>
    <tel>075-241-0191 (内線92-302)</tel>
    <geocode>135.769196,35.010492</geocode>
    <category>UNIV</category>
    <image/>
  </Library>
  <Library>
    <systemid>Univ_Taiwa</systemid>
    <systemname>キャリエールホテル旅行専門学校</systemname>
    <libkey>京栄校</libkey>
    <libid>121683</libid>
    <short>京都栄養医療専門学校情報ライブラリー</short>
    <formal>京都栄養医療専門学校情報ライブラリー</formal>
    <url_pc>http://library.taiwa.ac.jp/opac4/opac/Top</url_pc>
    <address>京都府京都市右京区嵯峨天龍寺瀬戸川町18−39</address>
    <pref>京都府</pref>
    <city>京都市</city>
    <post>616-8376</post>
    <tel>075-872-8500 [学校]</tel>
    <geocode>135.676266,35.019388</geocode>
    <category>UNIV</category>
    <image/>
  </Library>
</Libraries>
